Workbook

Sheet Register 2025-26
B5: OPERATIONAL RISK REGISTER 2025/26
A9: Link to Outcome | B9: Risk number | C9: Unit | D9: Risk Category | E9: Risk Description | F9: Risk Causes | G9: Consequences | H9: Impact Value (1-5) | I9: Likelihood Value (1-5) | J9: Inherent Risk Value | K9: Current controls | L9: Control Effectiveness | M9: Effectiveness rating | N9: Residual Risk Value | O9: Risk Appetite | P9: Risk Tolerance | Q9: Suggested Risk Response | R9: Risk Owner | S9: Action to improve management of the risk | T9: Action owner | U9: Timeline
A10: Enhanced governance for service delivery efficiency | B10: CS-1 | C10: Corporate Services | D10: Compliance / Regulatory | E10: Inadequate management of performance by supervisors | F10: Non-compliance with EPMDS policy Misalignment of Performance agreements to the Annual Performance Plan and Operational plan | G10: Late submission of PMDS documents Delays in the awarding of performance incentives Negative impact on expenditure projections Negative Audit report Inability to identify performance gaps timeously | H10: 4 | I10: 4 | J10: =H10*I10 -> 16 | K10: EPMDS policy EPMDS appeals committee EPMDS implementation plan Circulars on EPMDS Monitoring of PMDS documents on PERSAL EPMDS Templates EPMDS quality control checklist | L10: satisfactory | M10: =IF(L10="very good", 0.2, IF(L10="good", 0.4, IF(L10="Satisfactory", 0.6, IF(L10="weak", 0.8, IF(L10="non existent", 1))))) -> 0.6 | N10: =J10*M10 -> 9.6 | O10: =IF(N10<=4,"Acceptable ",IF(N10<=14,"Moderalety Acceptable","Unacceptable")) -> Moderalety Acceptable | P10: =IF(N10<=4,"Low Risk",IF(N10<=14,"Medium Risk","High Risk")) -> Medium Risk | Q10: =IF(P10="High Risk","Treatment",IF(P10="Medium Risk","Treatment","Tolerate")) -> Treatment | R10: Chief Director-Corporate Services | S10: Continuous implementation of EPMDS quality control checklist | T10: Director HRD &OD | U10: bi-annually
A11: Enhanced governance for service delivery efficiency | B11: CS-2 | C11: Corporate Services | D11: Compliance / Regulatory | E11: Incorrect record of Leave accruals | F11: Delays in submission of leave forms by management | G11: Overstating of AFS Negative audit opinion | H11: 4 | I11: 4 | J11: =H11*I11 -> 16 | K11: Leave management policy Triplicate leave form Attendance register Leave management tool Persal leave report | L11: very good | M11: =IF(L11="very good", 0.2, IF(L11="good", 0.4, IF(L11="Satisfactory", 0.6, IF(L11="weak", 0.8, IF(L11="non existent", 1))))) -> 0.2 | N11: =J11*M11 -> 3.2 | O11: =IF(N11<=4,"Acceptable ",IF(N11<=14,"Moderalety Acceptable","Unacceptable")) -> Acceptable | P11: =IF(N11<=4,"Low Risk",IF(N11<=14,"Medium Risk","High Risk")) -> Low Risk | Q11: =IF(P11="High Risk","Treatment",IF(P11="Medium Risk","Treatment","Tolerate")) -> Tolerate | R11: Chief Director: Corporate services | S11: Continue to monitor existing controls | T11: Director HRM | U11: Quarterly
A12: Enhanced governance for service delivery efficiency | B12: CS-3 | C12: Corporate Services | D12: Compliance / Regulatory | E12: Default Judgements | F12: The department does not serve and file a notice of intention to defend/oppose The department does not serve and file a notice of intention to defend/oppose/ timeously. The department fails to file a plea/opposing affidavit on a matter. The department enters a defective entry of intention to defend/oppose. | G12: High Legal Fees Fruitless and wasteful expenditure Negative audit outcome | H12: 4 | I12: 2 | J12: =H12*I12 -> 8 | K12: Circular issued to All Staff on the process for handling legal matters Circular on default judgement processes Circular on handling Legal Documents Litigation Policy Court Rules (Higher and Lower Courts) | L12: good | M12: =IF(L12="very good", 0.2, IF(L12="good", 0.4, IF(L12="Satisfactory", 0.6, IF(L12="weak", 0.8, IF(L12="non existent", 1))))) -> 0.4 | N12: =J12*M12 -> 3.2 | O12: =IF(N12<=4,"Acceptable ",IF(N12<=14,"Moderalety Acceptable","Unacceptable")) -> Acceptable | P12: =IF(N12<=4,"Low Risk",IF(N12<=14,"Medium Risk","High Risk")) -> Low Risk | Q12: =IF(P12="High Risk","Treatment",IF(P12="Medium Risk","Treatment","Tolerate")) -> Tolerate | R12: Director: Legal services | S12: Continue to monitor existing controls | U12: Quarterly
A13: Enhanced governance for service delivery efficiency | B13: ICT-01 | C13: Corporate Services | D13: Knowledge and Information Management | E13: Inadequate management of Departmental records and knowledge | F13: Ineffective utilisation of centralised registry services Non utilisation of the authorised departmental file plan Limited storage space for records keeping Inadequate records management capacity (Human Resources) in the department. e.g. Records Manager is not in the Organogram. Misaligned ICT Structure. Lack of knowledge management practices Non compliance with National and Provincial Archives Act | G13: Loss of Departmental information and knowledge Negative audit opinion Data breach Non preservation of institutional memory | H13: 5 | I13: 5 | J13: =H13*I13 -> 25 | K13: National Archives Act Records Management Policy Departmental file plan Procedure Manual Provincial Innovation & Knowledge Management Strategy . Innovation & Knowledge Managements champions appointed. Knowledge Hub (Departmental Website) National Human Settlements knowledge management strategy Succession Plan (HR) Physical records verification form ICT Digital Strategy, Information Systems Security (ISS) Strategy and Plan in place. Provincial Archives policy Secure offsite storage | L13: satisfactory | M13: =IF(L13="very good", 0.2, IF(L13="good", 0.4, IF(L13="Satisfactory", 0.6, IF(L13="weak", 0.8, IF(L13="non existent", 1))))) -> 0.6 | N13: =J13*M13 -> 15 | O13: =IF(N13<=4,"Acceptable ",IF(N13<=14,"Moderalety Acceptable","Unacceptable")) -> Unacceptable | P13: =IF(N13<=4,"Low Risk",IF(N13<=14,"Medium Risk","High Risk")) -> High Risk | Q13: =IF(P13="High Risk","Treatment",IF(P13="Medium Risk","Treatment","Tolerate")) -> Treatment | R13: Chief Director: Strategy and Systems | S13: Conduct awarenesses on records management Monitor the implementation of the records management policy Digitise and automate records management | T13: Director:GICTM | U13: Quarterly Quarterly Quarterly
A14: Socially cohesive and economically viable communities with access to basic services, housing, and economic opportunities | B14: HSFP-1 | C14: Human Settlements Facilitation Programme | D14: Service delivery | E14: Illegal occupation and use of houses | F14: Inadequate capacity at municipal level to manage beneficiary administration processes Manipulation of approved beneficiary lists Delays in project implementation Migration of beneficiaries | G14: Service delivery protests Rightful owners not occupying their houses | H14: 4 | I14: 5 | J14: =H14*I14 -> 20 | K14: Housing Subsidy System Housing Code Beneficiary Allocation Policy Beneficiary Allocation Committees Beneficiary correct occupation guidelines | L14: good | M14: =IF(L14="very good", 0.2, IF(L14="good", 0.4, IF(L14="Satisfactory", 0.6, IF(L14="weak", 0.8, IF(L14="non existent", 1))))) -> 0.4 | N14: =J14*M14 -> 8 | O14: =IF(N14<=4,"Acceptable ",IF(N14<=14,"Moderalety Acceptable","Unacceptable")) -> Moderalety Acceptable | P14: =IF(N14<=4,"Low Risk",IF(N14<=14,"Medium Risk","High Risk")) -> Medium Risk | Q14: =IF(P14="High Risk","Treatment",IF(P14="Medium Risk","Treatment","Tolerate")) -> Treatment | R14: Chief Director: Human Settlements Facilitation Programme | S14: Establishment and monitoring of Beneficiary Allocation Committees to ensure fairness in the allocation process and to avoid possible misallocation and wrongful occupation of houses Provide support to Municipalities regarding Beneficiary Administration | T14: Director: Beneficiary Management | U14: Quarterly Quarterly
A15: Socially cohesive and economically viable communities with access to basic services, housing, and economic opportunities | B15: HSFP-2 | C15: Human Settlements Facilitation Programme | D15: Service delivery | E15: Inadequate implementation of facilitation interventions | F15: Limited budget Lack of co-ordination within the department Lack of participation of key stakeholders | G15: Social unrest. Non compliance of consumers with the housing code. Growing trend of beneficiaries selling subsidised houses Limited understanding by beneficiaries of their rights and responsibilities | H15: 4 | I15: 4 | J15: =H15*I15 -> 16 | K15: Housing code . Consumer Education Framework Social Facilitation Strategy | L15: good | M15: =IF(L15="very good", 0.2, IF(L15="good", 0.4, IF(L15="Satisfactory", 0.6, IF(L15="weak", 0.8, IF(L15="non existent", 1))))) -> 0.4 | N15: =J15*M15 -> 6.4 | O15: =IF(N15<=4,"Acceptable ",IF(N15<=14,"Moderalety Acceptable","Unacceptable")) -> Moderalety Acceptable | P15: =IF(N15<=4,"Low Risk",IF(N15<=14,"Medium Risk","High Risk")) -> Medium Risk | Q15: =IF(P15="High Risk","Treatment",IF(P15="Medium Risk","Treatment","Tolerate")) -> Treatment | R15: Chief Director: Human Settlements Facilitation Programme | S15: Implementation of the Social Facilitation Strategy | T15: Director: Social Facilitation and Customer Care | U15: Quarterly
A16: Socially cohesive and economically viable communities with access to basic services, housing, and economic opportunities | B16: HSFP-3 | C16: Human Settlements Facilitation Programme | D16: Compliance / Regulatory | E16: Procurement of 40% MSMEs from the framework agreement may not be achieved. | F16: 1. There is currently no new projects dedicated to the MSMEs in the approved business plan. 2. MSME Framework Agreement could not be finalised due to the end of validity period which lapsed. 3. No Departmental policy that caters and enforce MSME procurement as the preferential procurement act does not adequately cover appointment of MSME but focuses on designated groups. | G16: Possibility of reputational damage since this was mentioned in the MEC's budget speech as one of the key priorities. | H16: 4 | I16: 5 | J16: =H16*I16 -> 20 | K16: Preferential Procurement Act Public Procurement Act | L16: weak | M16: =IF(L16="very good", 0.2, IF(L16="good", 0.4, IF(L16="Satisfactory", 0.6, IF(L16="weak", 0.8, IF(L16="non existent", 1))))) -> 0.8 | N16: =J16*M16 -> 16 | O16: =IF(N16<=4,"Acceptable ",IF(N16<=14,"Moderalety Acceptable","Unacceptable")) -> Unacceptable | P16: =IF(N16<=4,"Low Risk",IF(N16<=14,"Medium Risk","High Risk")) -> High Risk | Q16: =IF(P16="High Risk","Treatment",IF(P16="Medium Risk","Treatment","Tolerate")) -> Treatment | R16: Chief Director: Human Settlements Facilitation Programme | S16: Acquire lists of MSME contractors appointed by the region who are utilizing 40% of the Human Settlements’ Conditional Grant | T16: Director: Emerging Contractor Development | U16: Annually
A17: Socially cohesive and economically viable communities with access to basic services, housing, and economic opportunities | B17: HSFP-4 | C17: Human Settlements Facilitation Programme | D17: Compliance / Regulatory | E17: Inability for the department to provide input on skills development to unemployed youth (apprenticeship and learning ) | F17: Lack of departmental funding stream for artisan development programme. Dependence on external funding. | G17: Inability to provide artisan skills resource base for departmental projects Inability to develop Artisans. | H17: 3 | I17: 3 | J17: =H17*I17 -> 9 | K17: Annual MoU with Construction Education & Training Authority (CETA) CETA funding for eighty (80) learnership opportunities successfully secured | L17: weak | M17: =IF(L17="very good", 0.2, IF(L17="good", 0.4, IF(L17="Satisfactory", 0.6, IF(L17="weak", 0.8, IF(L17="non existent", 1))))) -> 0.8 | N17: =J17*M17 -> 7.2 | O17: =IF(N17<=4,"Acceptable ",IF(N17<=14,"Moderalety Acceptable","Unacceptable")) -> Moderalety Acceptable | P17: =IF(N17<=4,"Low Risk",IF(N17<=14,"Medium Risk","High Risk")) -> Medium Risk | Q17: =IF(P17="High Risk","Treatment",IF(P17="Medium Risk","Treatment","Tolerate")) -> Treatment | R17: Chief Director: Human Settlements Facilitation Programme | S17: Enhance working relationship with the Construction Education Training Authority (CETA) to receive funding permanently for funding the learnership and apprenticeship programmes. Allocation of funding from OPSAP | T17: Director: Emerging Contractor Development | U17: Annually
A18: Socially cohesive and economically viable communities with access to basic services, housing, and economic opportunities | B18: HSFP-5 | C18: Human Settlements Facilitation Programme | D18: Compliance / Regulatory | E18: Appointed contractors may not adequatly report on the number of jobs created | F18: 1. Appointed contractors do not attach and submit compliance documents such as the contracts between the contractor and EPWP participants, copies of the ID, copies of the attendance and payment registers. 2. Non adherence to current controls | G18: 1. Inadequate reports submitted by contractors get rejected by the EPWP Report System. 2. Target not achieved as a result of inadequate reports on the number of jobs created in Departmental projects submitted by appointed contractors. | H18: 4 | I18: 4 | J18: =H18*I18 -> 16 | K18: Full Adherence to EPWP Guidelines ( Attachment of the compliance documents on EPWP monthly reports by appointed contractors Full adherence to and signing off of the EPWP report checklist attached on payment certificate by Regional Directors to the Accounting Officer's directive pay appointed contractors for value created relative to their scope of work unless they submit fully compliant monthly reports) JBBC 5 Contract (MOU) in cooperation with the Department of Employment and Labor (DEL) to access unemployed labor for placement in Departmental projects when the need arises. | L18: satisfactory | M18: =IF(L18="very good", 0.2, IF(L18="good", 0.4, IF(L18="Satisfactory", 0.6, IF(L18="weak", 0.8, IF(L18="non existent", 1))))) -> 0.6 | N18: =J18*M18 -> 9.6 | O18: =IF(N18<=4,"Acceptable ",IF(N18<=14,"Moderalety Acceptable","Unacceptable")) -> Moderalety Acceptable | P18: =IF(N18<=4,"Low Risk",IF(N18<=14,"Medium Risk","High Risk")) -> Medium Risk | Q18: =IF(P18="High Risk","Treatment",IF(P18="Medium Risk","Treatment","Tolerate")) -> Treatment | R18: Chief Director: Human Settlements Facilitation Programme | S18: The Directorate of Emerging Contractors in cooperation with the Project Managers, EPWP Coordinators, Hands On Support and ECDPWI to collect compliant data from the appointed contractors Prepare an EPWP compliance checklist template for sign off by Project Manager, EPWP coordinator and the Regional Director. | T18: Director: Emerging Contractor Development | U18: Quarterly
A19: Socially cohesive and economically viable communities with access to basic services, housing, and economic opportunities | B19: HSFP-6 | C19: Human Settlements Facilitation Programme | D19: Compliance / Regulatory | E19: Procurement of 10% building materials from black industrialists may not be achieved since there is no policy provision and provision in the contracts of the appointed contractors | F19: 1. Lack of internal and external policy and framework supporting the procurement of materials from the black industirialists. 2. The East London Industrial Development Zone (ELDZ) does not have a target nor KPI to measure to support black industrialists in 2025/26 3. Provincial Treasury Instruction note 7 of 2016/17 does not cater for the procurement of building materials from Black Industrialists by contractors appointed. 4. Currently contracts of the appointed contractors do not have a provision for the procurement of building materials from the Black Industrialists by contractors appointed | G19: 1. Procurement of building material suppliers by contractors who are contracted with the department from 10 percent of the black industrialists may not be achieved. 2. This may cause reputational damage for the Departmen since the MEC pronounced in the budget policy speech as one of the priorities | H19: 4 | I19: 5 | J19: =H19*I19 -> 20 | K19: Black Industrialists 2015 Treasury Instruction Note 7; 2016/17 | L19: weak | M19: =IF(L19="very good", 0.2, IF(L19="good", 0.4, IF(L19="Satisfactory", 0.6, IF(L19="weak", 0.8, IF(L19="non existent", 1))))) -> 0.8 | N19: =J19*M19 -> 16 | O19: =IF(N19<=4,"Acceptable ",IF(N19<=14,"Moderalety Acceptable","Unacceptable")) -> Unacceptable | P19: =IF(N19<=4,"Low Risk",IF(N19<=14,"Medium Risk","High Risk")) -> High Risk | Q19: =IF(P19="High Risk","Treatment",IF(P19="Medium Risk","Treatment","Tolerate")) -> Treatment | R19: Chief Director: Human Settlements Facilitation Programme | S19: 1. Conduct a survey amongst the contractors appointed in all Departmental Regions to determine percentage of Black Industrialists whose building materials is being procured by appointed contractors. 2. Report on percentage of Black Industrialists whose building materials is procured by the contractors appointed 3. Recommend mechanisms for policy Implementation mechanism. | T19: Director: Emerging Contractor Development | U19: Annually
A20: Socially cohesive and economically viable communities with access to basic services, housing, and economic opportunities | B20: HSFP-7 | C20: Human Settlements Facilitation Programme | D20: Service delivery | E20: Delays in the processes of project approval | F20: Departmental Competing Priorities | G20: Lack of service delivery Underperformance by the department (financial and non financial) | H20: 3 | I20: 3 | J20: =H20*I20 -> 9 | K20: Housing Code Housing Policies Continuous implementation of Guideline for the project approval process. | L20: good | M20: =IF(L20="very good", 0.2, IF(L20="good", 0.4, IF(L20="Satisfactory", 0.6, IF(L20="weak", 0.8, IF(L20="non existent", 1))))) -> 0.4 | N20: =J20*M20 -> 3.6 | O20: =IF(N20<=4,"Acceptable ",IF(N20<=14,"Moderalety Acceptable","Unacceptable")) -> Acceptable | P20: =IF(N20<=4,"Low Risk",IF(N20<=14,"Medium Risk","High Risk")) -> Low Risk | Q20: =IF(P20="High Risk","Treatment",IF(P20="Medium Risk","Treatment","Tolerate")) -> Tolerate | R20: Chief Director: Human Settlements Facilitation Programme | S20: Continue to monitor existing controls | T20: Director: Beneficiary Management | U20: Quarterly
A21: Socially cohesive and economically viable communities with access to basic services, housing, and economic opportunities | B21: HSIP 1 | C21: Human Settlements Incremental Programs | D21: Third party performance | E21: Inadequate provision of temporary relief to emergency housing cases | F21: Inability of municipalities to perform the emergency housing assistance function Inadequate capacity of contractors to supply temporal shelters Limited budget against demand Unclear value chain process | G21: Violation of Human rights Exposure of people to vulnerability | H21: 4 | I21: 5 | J21: =H21*I21 -> 20 | K21: Housing Code Service level agreement with appointed contactors Disaster Management Act Supply Chain Management Policy | L21: good | M21: =IF(L21="very good", 0.2, IF(L21="good", 0.4, IF(L21="Satisfactory", 0.6, IF(L21="weak", 0.8, IF(L21="non existent", 1))))) -> 0.4 | N21: =J21*M21 -> 8 | O21: =IF(N21<=4,"Acceptable ",IF(N21<=14,"Moderalety Acceptable","Unacceptable")) -> Moderalety Acceptable | P21: =IF(N21<=4,"Low Risk",IF(N21<=14,"Medium Risk","High Risk")) -> Medium Risk | Q21: =IF(P21="High Risk","Treatment",IF(P21="Medium Risk","Treatment","Tolerate")) -> Treatment | R21: Chief Director: Human Settlements Incremental Programs | S21: Engage and support relevant stakeholders on policy implementation | T21: Director: Emergency Housing and EPHP | U21: Quarterly
A22: Socially cohesive and economically viable communities with access to basic services, housing, and economic opportunities | B22: HSIP 2 | C22: Human Settlements Incremental Programs | D22: Third party performance | E22: Inconsistence in the implementation of the EPHP programme | F22: Limited understanding of the EPHP policy and its implementation by role-players Lack of capacity by CRO's to implement the programme | G22: Blocked projects Inability to achieve the objectives of the policy | H22: 4 | I22: 5 | J22: =H22*I22 -> 20 | K22: Housing code EPHP provincial guidelines | L22: satisfactory | M22: =IF(L22="very good", 0.2, IF(L22="good", 0.4, IF(L22="Satisfactory", 0.6, IF(L22="weak", 0.8, IF(L22="non existent", 1))))) -> 0.6 | N22: =J22*M22 -> 12 | O22: =IF(N22<=4,"Acceptable ",IF(N22<=14,"Moderalety Acceptable","Unacceptable")) -> Moderalety Acceptable | P22: =IF(N22<=4,"Low Risk",IF(N22<=14,"Medium Risk","High Risk")) -> Medium Risk | Q22: =IF(P22="High Risk","Treatment",IF(P22="Medium Risk","Treatment","Tolerate")) -> Treatment | R22: Chief Director: Human Settlements Incremental Programs | S22: Conduct workshops for appointed CRO's to reinforce the understanding Engage stakeholders to align to the implementation of the EPHP Establishment of the CRO panel for capacity enhancement through SCM processes | T22: Director: Emergency Housing and EPHP | U22: 30/09/2025 30/09/2025 31/03/2026
A23: Socially cohesive and economically viable communities with access to basic services, housing, and economic opportunities | B23: HSIP 3 | C23: Human Settlements Incremental Programs | D23: Service delivery | E23: Inability to upgrade informal settlements to the desired phases 1, 2 & 3 | F23: Lack of bulk infrastructure Poor alignment of the implementing partners to the delivery outputs Challenges in land assembly Lack of enforcement of conditions of contract | G23: Social unrest Failure to achieve tenure security , Health security and community empowerment (Water & Sanitation) Non provision of housing opportunities to qualifying beneficiaries | H23: 4 | I23: 4 | J23: =H23*I23 -> 16 | K23: Housing code National informal settlements upgrading framework (DORA) Province wide upgrading strategy National Department of Human Settlements Upgrading framework | L23: satisfactory | M23: =IF(L23="very good", 0.2, IF(L23="good", 0.4, IF(L23="Satisfactory", 0.6, IF(L23="weak", 0.8, IF(L23="non existent", 1))))) -> 0.6 | N23: =J23*M23 -> 9.6 | O23: =IF(N23<=4,"Acceptable ",IF(N23<=14,"Moderalety Acceptable","Unacceptable")) -> Moderalety Acceptable | P23: =IF(N23<=4,"Low Risk",IF(N23<=14,"Medium Risk","High Risk")) -> Medium Risk | Q23: =IF(P23="High Risk","Treatment",IF(P23="Medium Risk","Treatment","Tolerate")) -> Treatment | R23: Chief Director: Human Settlements Incremental Programs | S23: Review province wide upgrading strategy to align with DORA and the National Human Settlements upgrading framework Strengthen partnerships with delivery stakeholders Enhance social facilitation and awareness Enforcement of contractual terms and conditions | T23: Director: Informal Settlements Upgrading | U23: 30/09/2025 Quarterly Quarterly Quarterly
A24: Improved tenure security and expanded access to affordable housing through innovative funding models and partnerships | B24: HSPA- 01 | C24: Human Settlements Property and Assets | D24: Service delivery | E24: Inadequate devolution of land parcels to municipalities | F24: Municipalities refusing to accept offered land parcels Delays in council resolutions Delays by state attorney in appointing correspondents | G24: Land invasion Social unrest/protests Illegal occupation | H24: 5 | I24: 5 | J24: =H24*I24 -> 25 | K24: Section 14 and 15 of Housing Act 107 of 1997 as amended Housing Code Deeds Registry Act 43 of 1937 State Land disposal Act | L24: satisfactory | M24: =IF(L24="very good", 0.2, IF(L24="good", 0.4, IF(L24="Satisfactory", 0.6, IF(L24="weak", 0.8, IF(L24="non existent", 1))))) -> 0.6 | N24: =J24*M24 -> 15 | O24: =IF(N24<=4,"Acceptable ",IF(N24<=14,"Moderalety Acceptable","Unacceptable")) -> Unacceptable | P24: =IF(N24<=4,"Low Risk",IF(N24<=14,"Medium Risk","High Risk")) -> High Risk | Q24: =IF(P24="High Risk","Treatment",IF(P24="Medium Risk","Treatment","Tolerate")) -> Treatment | R24: Chief Director: Housing Property Management | S24: Engage municipalities to provide council resolutions/regulations and or development plans inline with the land to be devolved Engage state attorney to ensure timeous appointment of correspondents | T24: Director: Land Acquisition and Tenure Services | U24: Quarterly Quarterly
... A47: Enhanced governance for service delivery efficiency | B47: SM-04 | C47: Strategy and Systems | D47: Service delivery | E47: Inconsistent stakeholder participation in integrated Human Settlements delivery | F47: Inconsistent support by external stakeholders in Human Settlements programmes | G47: Non delivery of integrated human settlements mandate | H47: 4 | I47: 4 | J47: =H47*I47 -> 16 | K47: Stakeholder engagement and IGR strategy IGR tracking tool Provincial and municipal IGR structures | L47: satisfactory | M47: =IF(L47="very good", 0.2, IF(L47="good", 0.4, IF(L47="Satisfactory", 0.6, IF(L47="weak", 0.8, IF(L47="non existent", 1))))) -> 0.6 | N47: =J47*M47 -> 9.6 | O47: =IF(N47<=4,"Acceptable ",IF(N47<=14,"Moderalety Acceptable","Unacceptable")) -> Moderalety Acceptable | P47: =IF(N47<=4,"Low Risk",IF(N47<=14,"Medium Risk","High Risk")) -> Medium Risk | Q47: =IF(P47="High Risk","Treatment",IF(P47="Medium Risk","Treatment","Tolerate")) -> Treatment | R47: Chief Director: Strategy and Systems | S47: Implementation of the stakeholder engagement and IGR action plan Co-ordinate MEC (Member of the Executive Council) and MMC (Member of the Municipal Council) engagements | T47: Director: Stakeholder Engagement | U47: Quarterly Quarterly
A48: Signature: __________________
A50: Date: __________________

Sheet Sheet3
A1: Link to Outcome | B1: Risk number | C1: Risk Category | D1: Risk Name | E1: Risk Description | F1: Risk Causes | G1: Consequences | H1: Impact Value (1-5) | I1: Likelihood Value (1-5) | J1: Inherent Risk Value | K1: Current controls | L1: Control Effectiveness | M1: Effectiveness rating | N1: Residual Risk Value | O1: Risk Appetite | P1: Risk Tolerance | Q1: Risk Response Treatment | R1: Risk Owner | S1: Action to improve management of the risk | T1: Action owner | U1: Timeline | V1: Current Status
A2: Good Governance | B2: FR1 | E2: Misrepresentation of facts ….. | F2: Submission of falsified Curriculum Vitae (s) Crafting and certification of fictitious variation orders/difficult terrain Certification of fictitious milestones achievements Submission of fictitious Claims submitted by service provider to deliberate deception the Department . i.e duplicate claims , non existences , claims for the working that is done or uncompleted work Manipulation of beneficiary Lists for shelters .i.e Beneficairy that are not in need of temparary shelters reflecting on the request list Collusion between officials and service provider to submit fraudulent claims i.e .inflated prices | G2: Fruitless and wasteful expenditure No value created Financial Losses Reputational damage to government/ Department Litgation cases | H2: 3 | I2: 3 | J2: =H2*I2 -> 9 | L2: Satisfactory | M2: =IF(L2="very good", 0.2, IF(L2="good", 0.4, IF(L2="Satisfactory", 0.6, IF(L2="weak", 0.8, IF(L2="non existent", 1))))) -> 0.6 | N2: =J2*M2 -> 5.4 | O2: =IF(N2<=4,"Acceptable ",IF(N2<=14,"Moderalety Acceptable","Unacceptable")) -> Moderalety Acceptable | P2: =IF(N2<=4,"Low Risk",IF(N2<=14,"Medium Risk","High Risk")) -> Medium Risk | Q2: =IF(P2="High Risk","Treatment",IF(P2="Medium Risk","Treatment","Tolerate")) -> Treatment
A3: Good Governance | B3: FR2 | E3: Bribery….. | F3: Bribery of Community Liason Officer(s) for employment of cheap labour and foreign employees. Manipulation of Project Steering Committee (PSC) by Councillor(s), Clo(s) and Contractors Prioritisation of un-approved beneficiaries on projects and manipulation of community employee lists Possible manipulation of the Emerging contractors list to benefit towards the 30% subcontractors Employees accepting bribes from contractors for fictitiious variation oders and to fast track payment of claims. | G3: Social unrest Slow progress on site Halted and blocked projects Social unrest Slow progress on site Halted and blocked projects Poor quality of projects Delay in service delivery, blocked and halted projects Poor quality on projects | H3: 3 | I3: 3 | J3: =H3*I3 -> 9 | L3: Satisfactory | M3: =IF(L3="very good", 0.2, IF(L3="good", 0.4, IF(L3="Satisfactory", 0.6, IF(L3="weak", 0.8, IF(L3="non existent", 1))))) -> 0.6 | N3: =J3*M3 -> 5.4 | O3: =IF(N3<=4,"Acceptable ",IF(N3<=14,"Moderalety Acceptable","Unacceptable")) -> Moderalety Acceptable | P3: =IF(N3<=4,"Low Risk",IF(N3<=14,"Medium Risk","High Risk")) -> Medium Risk | Q3: =IF(P3="High Risk","Treatment",IF(P3="Medium Risk","Treatment","Tolerate")) -> Treatment
A4: Good Governance | B4: FR3 | E4: Collusion ….. To gain kickbacks | F4: Collusion between project managers and subcontractors Officials may have opportunity to fast-track other invoices against others for kickbacks (rationalise the act) Substitute materials while billing for higher quality or falsification of pay applications Manipulation of procurement processes to favour specific bidder(s)/supplier(s). | G4: Image of Department is compromised/Dented (Labelling) Poor control system | H4: 3 | I4: 3 | J4: =H4*I4 -> 9 | L4: Satisfactory | M4: =IF(L4="very good", 0.2, IF(L4="good", 0.4, IF(L4="Satisfactory", 0.6, IF(L4="weak", 0.8, IF(L4="non existent", 1))))) -> 0.6 | N4: =J4*M4 -> 5.4 | O4: =IF(N4<=4,"Acceptable ",IF(N4<=14,"Moderalety Acceptable","Unacceptable")) -> Moderalety Acceptable | P4: =IF(N4<=4,"Low Risk",IF(N4<=14,"Medium Risk","High Risk")) -> Medium Risk | Q4: =IF(P4="High Risk","Treatment",IF(P4="Medium Risk","Treatment","Tolerate")) -> Treatment
A5: Good Governance | B5: FR4 | H5: 3 | I5: 3 | J5: =H5*I5 -> 9 | L5: Satisfactory | M5: =IF(L5="very good", 0.2, IF(L5="good", 0.4, IF(L5="Satisfactory", 0.6, IF(L5="weak", 0.8, IF(L5="non existent", 1))))) -> 0.6 | N5: =J5*M5 -> 5.4 | O5: =IF(N5<=4,"Acceptable ",IF(N5<=14,"Moderalety Acceptable","Unacceptable")) -> Moderalety Acceptable | P5: =IF(N5<=4,"Low Risk",IF(N5<=14,"Medium Risk","High Risk")) -> Medium Risk | Q5: =IF(P5="High Risk","Treatment",IF(P5="Medium Risk","Treatment","Tolerate")) -> Treatment
A6: Good Governance | B6: FR5 | H6: 3 | I6: 3 | J6: =H6*I6 -> 9 | L6: Satisfactory | M6: =IF(L6="very good", 0.2, IF(L6="good", 0.4, IF(L6="Satisfactory", 0.6, IF(L6="weak", 0.8, IF(L6="non existent", 1))))) -> 0.6 | N6: =J6*M6 -> 5.4 | O6: =IF(N6<=4,"Acceptable ",IF(N6<=14,"Moderalety Acceptable","Unacceptable")) -> Moderalety Acceptable | P6: =IF(N6<=4,"Low Risk",IF(N6<=14,"Medium Risk","High Risk")) -> Medium Risk | Q6: =IF(P6="High Risk","Treatment",IF(P6="Medium Risk","Treatment","Tolerate")) -> Treatment
A7: Good Governance | B7: FR6 | H7: 3 | I7: 3 | J7: =H7*I7 -> 9 | L7: Satisfactory | M7: =IF(L7="very good", 0.2, IF(L7="good", 0.4, IF(L7="Satisfactory", 0.6, IF(L7="weak", 0.8, IF(L7="non existent", 1))))) -> 0.6 | N7: =J7*M7 -> 5.4 | O7: =IF(N7<=4,"Acceptable ",IF(N7<=14,"Moderalety Acceptable","Unacceptable")) -> Moderalety Acceptable | P7: =IF(N7<=4,"Low Risk",IF(N7<=14,"Medium Risk","High Risk")) -> Medium Risk | Q7: =IF(P7="High Risk","Treatment",IF(P7="Medium Risk","Treatment","Tolerate")) -> Treatment
A8: Good Governance | B8: FR7 | H8: 3 | I8: 3 | J8: =H8*I8 -> 9 | L8: Satisfactory | M8: =IF(L8="very good", 0.2, IF(L8="good", 0.4, IF(L8="Satisfactory", 0.6, IF(L8="weak", 0.8, IF(L8="non existent", 1))))) -> 0.6 | N8: =J8*M8 -> 5.4 | O8: =IF(N8<=4,"Acceptable ",IF(N8<=14,"Moderalety Acceptable","Unacceptable")) -> Moderalety Acceptable | P8: =IF(N8<=4,"Low Risk",IF(N8<=14,"Medium Risk","High Risk")) -> Medium Risk | Q8: =IF(P8="High Risk","Treatment",IF(P8="Medium Risk","Treatment","Tolerate")) -> Treatment
A9: Good Governance | B9: FR8 | H9: 3 | I9: 3 | J9: =H9*I9 -> 9 | L9: Satisfactory | M9: =IF(L9="very good", 0.2, IF(L9="good", 0.4, IF(L9="Satisfactory", 0.6, IF(L9="weak", 0.8, IF(L9="non existent", 1))))) -> 0.6 | N9: =J9*M9 -> 5.4 | O9: =IF(N9<=4,"Acceptable ",IF(N9<=14,"Moderalety Acceptable","Unacceptable")) -> Moderalety Acceptable | P9: =IF(N9<=4,"Low Risk",IF(N9<=14,"Medium Risk","High Risk")) -> Medium Risk | Q9: =IF(P9="High Risk","Treatment",IF(P9="Medium Risk","Treatment","Tolerate")) -> Treatment
A10: Good Governance | B10: FR9 | H10: 3 | I10: 3 | J10: =H10*I10 -> 9 | L10: Satisfactory | M10: =IF(L10="very good", 0.2, IF(L10="good", 0.4, IF(L10="Satisfactory", 0.6, IF(L10="weak", 0.8, IF(L10="non existent", 1))))) -> 0.6 | N10: =J10*M10 -> 5.4 | O10: =IF(N10<=4,"Acceptable ",IF(N10<=14,"Moderalety Acceptable","Unacceptable")) -> Moderalety Acceptable | P10: =IF(N10<=4,"Low Risk",IF(N10<=14,"Medium Risk","High Risk")) -> Medium Risk | Q10: =IF(P10="High Risk","Treatment",IF(P10="Medium Risk","Treatment","Tolerate")) -> Treatment
A11: Good Governance | B11: FR10 | H11: 3 | I11: 3 | J11: =H11*I11 -> 9 | L11: Satisfactory | M11: =IF(L11="very good", 0.2, IF(L11="good", 0.4, IF(L11="Satisfactory", 0.6, IF(L11="weak", 0.8, IF(L11="non existent", 1))))) -> 0.6 | N11: =J11*M11 -> 5.4 | O11: =IF(N11<=4,"Acceptable ",IF(N11<=14,"Moderalety Acceptable","Unacceptable")) -> Moderalety Acceptable | P11: =IF(N11<=4,"Low Risk",IF(N11<=14,"Medium Risk","High Risk")) -> Medium Risk | Q11: =IF(P11="High Risk","Treatment",IF(P11="Medium Risk","Treatment","Tolerate")) -> Treatment
B12: FR11 | H12: 3 | I12: 3 | J12: =H12*I12 -> 9 | L12: Satisfactory | M12: =IF(L12="very good", 0.2, IF(L12="good", 0.4, IF(L12="Satisfactory", 0.6, IF(L12="weak", 0.8, IF(L12="non existent", 1))))) -> 0.6 | N12: =J12*M12 -> 5.4 | O12: =IF(N12<=4,"Acceptable ",IF(N12<=14,"Moderalety Acceptable","Unacceptable")) -> Moderalety Acceptable | P12: =IF(N12<=4,"Low Risk",IF(N12<=14,"Medium Risk","High Risk")) -> Medium Risk | Q12: =IF(P12="High Risk","Treatment",IF(P12="Medium Risk","Treatment","Tolerate")) -> Treatment
B13: FR12 | H13: 3 | I13: 3 | J13: =H13*I13 -> 9 | L13: Satisfactory | M13: =IF(L13="very good", 0.2, IF(L13="good", 0.4, IF(L13="Satisfactory", 0.6, IF(L13="weak", 0.8, IF(L13="non existent", 1))))) -> 0.6 | N13: =J13*M13 -> 5.4 | O13: =IF(N13<=4,"Acceptable ",IF(N13<=14,"Moderalety Acceptable","Unacceptable")) -> Moderalety Acceptable | P13: =IF(N13<=4,"Low Risk",IF(N13<=14,"Medium Risk","High Risk")) -> Medium Risk | Q13: =IF(P13="High Risk","Treatment",IF(P13="Medium Risk","Treatment","Tolerate")) -> Treatment
B14: FR13 | H14: 3 | I14: 3 | J14: =H14*I14 -> 9 | L14: Satisfactory | M14: =IF(L14="very good", 0.2, IF(L14="good", 0.4, IF(L14="Satisfactory", 0.6, IF(L14="weak", 0.8, IF(L14="non existent", 1))))) -> 0.6 | N14: =J14*M14 -> 5.4 | O14: =IF(N14<=4,"Acceptable ",IF(N14<=14,"Moderalety Acceptable","Unacceptable")) -> Moderalety Acceptable | P14: =IF(N14<=4,"Low Risk",IF(N14<=14,"Medium Risk","High Risk")) -> Medium Risk | Q14: =IF(P14="High Risk","Treatment",IF(P14="Medium Risk","Treatment","Tolerate")) -> Treatment
B15: FR14 | H15: 3 | I15: 3 | J15: =H15*I15 -> 9 | L15: Satisfactory | M15: =IF(L15="very good", 0.2, IF(L15="good", 0.4, IF(L15="Satisfactory", 0.6, IF(L15="weak", 0.8, IF(L15="non existent", 1))))) -> 0.6 | N15: =J15*M15 -> 5.4 | O15: =IF(N15<=4,"Acceptable ",IF(N15<=14,"Moderalety Acceptable","Unacceptable")) -> Moderalety Acceptable | P15: =IF(N15<=4,"Low Risk",IF(N15<=14,"Medium Risk","High Risk")) -> Medium Risk | Q15: =IF(P15="High Risk","Treatment",IF(P15="Medium Risk","Treatment","Tolerate")) -> Treatment
B16: FR15 | H16: 3 | I16: 3 | J16: =H16*I16 -> 9 | L16: Satisfactory | M16: =IF(L16="very good", 0.2, IF(L16="good", 0.4, IF(L16="Satisfactory", 0.6, IF(L16="weak", 0.8, IF(L16="non existent", 1))))) -> 0.6 | N16: =J16*M16 -> 5.4 | O16: =IF(N16<=4,"Acceptable ",IF(N16<=14,"Moderalety Acceptable","Unacceptable")) -> Moderalety Acceptable | P16: =IF(N16<=4,"Low Risk",IF(N16<=14,"Medium Risk","High Risk")) -> Medium Risk | Q16: =IF(P16="High Risk","Treatment",IF(P16="Medium Risk","Treatment","Tolerate")) -> Treatment
B17: FR16 | H17: 3 | I17: 3 | J17: =H17*I17 -> 9 | L17: Satisfactory | M17: =IF(L17="very good", 0.2, IF(L17="good", 0.4, IF(L17="Satisfactory", 0.6, IF(L17="weak", 0.8, IF(L17="non existent", 1))))) -> 0.6 | N17: =J17*M17 -> 5.4 | O17: =IF(N17<=4,"Acceptable ",IF(N17<=14,"Moderalety Acceptable","Unacceptable")) -> Moderalety Acceptable | P17: =IF(N17<=4,"Low Risk",IF(N17<=14,"Medium Risk","High Risk")) -> Medium Risk | Q17: =IF(P17="High Risk","Treatment",IF(P17="Medium Risk","Treatment","Tolerate")) -> Treatment
B18: FR17 | H18: 3 | I18: 3 | J18: =H18*I18 -> 9 | L18: Satisfactory | M18: =IF(L18="very good", 0.2, IF(L18="good", 0.4, IF(L18="Satisfactory", 0.6, IF(L18="weak", 0.8, IF(L18="non existent", 1))))) -> 0.6 | N18: =J18*M18 -> 5.4 | O18: =IF(N18<=4,"Acceptable ",IF(N18<=14,"Moderalety Acceptable","Unacceptable")) -> Moderalety Acceptable | P18: =IF(N18<=4,"Low Risk",IF(N18<=14,"Medium Risk","High Risk")) -> Medium Risk | Q18: =IF(P18="High Risk","Treatment",IF(P18="Medium Risk","Treatment","Tolerate")) -> Treatment
B19: FR18 | H19: 3 | I19: 3 | J19: =H19*I19 -> 9 | L19: Satisfactory | M19: =IF(L19="very good", 0.2, IF(L19="good", 0.4, IF(L19="Satisfactory", 0.6, IF(L19="weak", 0.8, IF(L19="non existent", 1))))) -> 0.6 | N19: =J19*M19 -> 5.4 | O19: =IF(N19<=4,"Acceptable ",IF(N19<=14,"Moderalety Acceptable","Unacceptable")) -> Moderalety Acceptable | P19: =IF(N19<=4,"Low Risk",IF(N19<=14,"Medium Risk","High Risk")) -> Medium Risk | Q19: =IF(P19="High Risk","Treatment",IF(P19="Medium Risk","Treatment","Tolerate")) -> Treatment
B20: FR19 | H20: 3 | I20: 3 | J20: =H20*I20 -> 9 | L20: Satisfactory | M20: =IF(L20="very good", 0.2, IF(L20="good", 0.4, IF(L20="Satisfactory", 0.6, IF(L20="weak", 0.8, IF(L20="non existent", 1))))) -> 0.6 | N20: =J20*M20 -> 5.4 | O20: =IF(N20<=4,"Acceptable ",IF(N20<=14,"Moderalety Acceptable","Unacceptable")) -> Moderalety Acceptable | P20: =IF(N20<=4,"Low Risk",IF(N20<=14,"Medium Risk","High Risk")) -> Medium Risk | Q20: =IF(P20="High Risk","Treatment",IF(P20="Medium Risk","Treatment","Tolerate")) -> Treatment
B21: FR20 | H21: 3 | I21: 3 | J21: =H21*I21 -> 9 | L21: Satisfactory | M21: =IF(L21="very good", 0.2, IF(L21="good", 0.4, IF(L21="Satisfactory", 0.6, IF(L21="weak", 0.8, IF(L21="non existent", 1))))) -> 0.6 | N21: =J21*M21 -> 5.4 | O21: =IF(N21<=4,"Acceptable ",IF(N21<=14,"Moderalety Acceptable","Unacceptable")) -> Moderalety Acceptable | P21: =IF(N21<=4,"Low Risk",IF(N21<=14,"Medium Risk","High Risk")) -> Medium Risk | Q21: =IF(P21="High Risk","Treatment",IF(P21="Medium Risk","Treatment","Tolerate")) -> Treatment
B22: FR21 | H22: 3 | I22: 3 | J22: =H22*I22 -> 9 | L22: Satisfactory | M22: =IF(L22="very good", 0.2, IF(L22="good", 0.4, IF(L22="Satisfactory", 0.6, IF(L22="weak", 0.8, IF(L22="non existent", 1))))) -> 0.6 | N22: =J22*M22 -> 5.4 | O22: =IF(N22<=4,"Acceptable ",IF(N22<=14,"Moderalety Acceptable","Unacceptable")) -> Moderalety Acceptable | P22: =IF(N22<=4,"Low Risk",IF(N22<=14,"Medium Risk","High Risk")) -> Medium Risk | Q22: =IF(P22="High Risk","Treatment",IF(P22="Medium Risk","Treatment","Tolerate")) -> Treatment
B23: FR22 | H23: 3 | I23: 3 | J23: =H23*I23 -> 9 | L23: Satisfactory | M23: =IF(L23="very good", 0.2, IF(L23="good", 0.4, IF(L23="Satisfactory", 0.6, IF(L23="weak", 0.8, IF(L23="non existent", 1))))) -> 0.6 | N23: =J23*M23 -> 5.4 | O23: =IF(N23<=4,"Acceptable ",IF(N23<=14,"Moderalety Acceptable","Unacceptable")) -> Moderalety Acceptable | P23: =IF(N23<=4,"Low Risk",IF(N23<=14,"Medium Risk","High Risk")) -> Medium Risk | Q23: =IF(P23="High Risk","Treatment",IF(P23="Medium Risk","Treatment","Tolerate")) -> Treatment
... B36: FR35 | H36: 3 | I36: 3 | J36: =H36*I36 -> 9 | L36: Satisfactory | M36: =IF(L36="very good", 0.2, IF(L36="good", 0.4, IF(L36="Satisfactory", 0.6, IF(L36="weak", 0.8, IF(L36="non existent", 1))))) -> 0.6 | N36: =J36*M36 -> 5.4 | O36: =IF(N36<=4,"Acceptable ",IF(N36<=14,"Moderalety Acceptable","Unacceptable")) -> Moderalety Acceptable | P36: =IF(N36<=4,"Low Risk",IF(N36<=14,"Medium Risk","High Risk")) -> Medium Risk | Q36: =IF(P36="High Risk","Treatment",IF(P36="Medium Risk","Treatment","Tolerate")) -> Treatment
H37: 3 | I37: 3 | J37: =H37*I37 -> 9 | L37: Satisfactory | M37: =IF(L37="very good", 0.2, IF(L37="good", 0.4, IF(L37="Satisfactory", 0.6, IF(L37="weak", 0.8, IF(L37="non existent", 1))))) -> 0.6 | N37: =J37*M37 -> 5.4 | O37: =IF(N37<=4,"Acceptable ",IF(N37<=14,"Moderalety Acceptable","Unacceptable")) -> Moderalety Acceptable | P37: =IF(N37<=4,"Low Risk",IF(N37<=14,"Medium Risk","High Risk")) -> Medium Risk | Q37: =IF(P37="High Risk","Treatment",IF(P37="Medium Risk","Treatment","Tolerate")) -> Treatment
H38: 3 | I38: 3 | J38: =H38*I38 -> 9 | L38: Satisfactory | M38: =IF(L38="very good", 0.2, IF(L38="good", 0.4, IF(L38="Satisfactory", 0.6, IF(L38="weak", 0.8, IF(L38="non existent", 1))))) -> 0.6 | N38: =J38*M38 -> 5.4 | O38: =IF(N38<=4,"Acceptable ",IF(N38<=14,"Moderalety Acceptable","Unacceptable")) -> Moderalety Acceptable | P38: =IF(N38<=4,"Low Risk",IF(N38<=14,"Medium Risk","High Risk")) -> Medium Risk | Q38: =IF(P38="High Risk","Treatment",IF(P38="Medium Risk","Treatment","Tolerate")) -> Treatment
H39: 3 | I39: 3 | J39: =H39*I39 -> 9 | L39: Satisfactory | M39: =IF(L39="very good", 0.2, IF(L39="good", 0.4, IF(L39="Satisfactory", 0.6, IF(L39="weak", 0.8, IF(L39="non existent", 1))))) -> 0.6 | N39: =J39*M39 -> 5.4 | O39: =IF(N39<=4,"Acceptable ",IF(N39<=14,"Moderalety Acceptable","Unacceptable")) -> Moderalety Acceptable | P39: =IF(N39<=4,"Low Risk",IF(N39<=14,"Medium Risk","High Risk")) -> Medium Risk | Q39: =IF(P39="High Risk","Treatment",IF(P39="Medium Risk","Treatment","Tolerate")) -> Treatment
H40: 3 | I40: 3 | J40: =H40*I40 -> 9 | L40: Satisfactory | M40: =IF(L40="very good", 0.2, IF(L40="good", 0.4, IF(L40="Satisfactory", 0.6, IF(L40="weak", 0.8, IF(L40="non existent", 1))))) -> 0.6 | N40: =J40*M40 -> 5.4 | O40: =IF(N40<=4,"Acceptable ",IF(N40<=14,"Moderalety Acceptable","Unacceptable")) -> Moderalety Acceptable | P40: =IF(N40<=4,"Low Risk",IF(N40<=14,"Medium Risk","High Risk")) -> Medium Risk | Q40: =IF(P40="High Risk","Treatment",IF(P40="Medium Risk","Treatment","Tolerate")) -> Treatment
H41: 3 | I41: 3 | J41: =H41*I41 -> 9 | L41: Satisfactory | M41: =IF(L41="very good", 0.2, IF(L41="good", 0.4, IF(L41="Satisfactory", 0.6, IF(L41="weak", 0.8, IF(L41="non existent", 1))))) -> 0.6 | N41: =J41*M41 -> 5.4 | O41: =IF(N41<=4,"Acceptable ",IF(N41<=14,"Moderalety Acceptable","Unacceptable")) -> Moderalety Acceptable | P41: =IF(N41<=4,"Low Risk",IF(N41<=14,"Medium Risk","High Risk")) -> Medium Risk | Q41: =IF(P41="High Risk","Treatment",IF(P41="Medium Risk","Treatment","Tolerate")) -> Treatment
H42: 3 | I42: 3 | J42: =H42*I42 -> 9 | L42: Satisfactory | M42: =IF(L42="very good", 0.2, IF(L42="good", 0.4, IF(L42="Satisfactory", 0.6, IF(L42="weak", 0.8, IF(L42="non existent", 1))))) -> 0.6 | N42: =J42*M42 -> 5.4 | O42: =IF(N42<=4,"Acceptable ",IF(N42<=14,"Moderalety Acceptable","Unacceptable")) -> Moderalety Acceptable | P42: =IF(N42<=4,"Low Risk",IF(N42<=14,"Medium Risk","High Risk")) -> Medium Risk | Q42: =IF(P42="High Risk","Treatment",IF(P42="Medium Risk","Treatment","Tolerate")) -> Treatment
H43: 3 | I43: 3 | J43: =H43*I43 -> 9 | L43: Satisfactory | M43: =IF(L43="very good", 0.2, IF(L43="good", 0.4, IF(L43="Satisfactory", 0.6, IF(L43="weak", 0.8, IF(L43="non existent", 1))))) -> 0.6 | N43: =J43*M43 -> 5.4 | O43: =IF(N43<=4,"Acceptable ",IF(N43<=14,"Moderalety Acceptable","Unacceptable")) -> Moderalety Acceptable | P43: =IF(N43<=4,"Low Risk",IF(N43<=14,"Medium Risk","High Risk")) -> Medium Risk | Q43: =IF(P43="High Risk","Treatment",IF(P43="Medium Risk","Treatment","Tolerate")) -> Treatment
H44: 3 | I44: 3 | J44: =H44*I44 -> 9 | L44: Satisfactory | M44: =IF(L44="very good", 0.2, IF(L44="good", 0.4, IF(L44="Satisfactory", 0.6, IF(L44="weak", 0.8, IF(L44="non existent", 1))))) -> 0.6 | N44: =J44*M44 -> 5.4 | O44: =IF(N44<=4,"Acceptable ",IF(N44<=14,"Moderalety Acceptable","Unacceptable")) -> Moderalety Acceptable | P44: =IF(N44<=4,"Low Risk",IF(N44<=14,"Medium Risk","High Risk")) -> Medium Risk | Q44: =IF(P44="High Risk","Treatment",IF(P44="Medium Risk","Treatment","Tolerate")) -> Treatment
H45: 3 | I45: 3 | J45: =H45*I45 -> 9 | L45: Satisfactory | M45: =IF(L45="very good", 0.2, IF(L45="good", 0.4, IF(L45="Satisfactory", 0.6, IF(L45="weak", 0.8, IF(L45="non existent", 1))))) -> 0.6 | N45: =J45*M45 -> 5.4 | O45: =IF(N45<=4,"Acceptable ",IF(N45<=14,"Moderalety Acceptable","Unacceptable")) -> Moderalety Acceptable | P45: =IF(N45<=4,"Low Risk",IF(N45<=14,"Medium Risk","High Risk")) -> Medium Risk | Q45: =IF(P45="High Risk","Treatment",IF(P45="Medium Risk","Treatment","Tolerate")) -> Treatment
H46: 3 | I46: 3 | J46: =H46*I46 -> 9 | L46: Satisfactory | M46: =IF(L46="very good", 0.2, IF(L46="good", 0.4, IF(L46="Satisfactory", 0.6, IF(L46="weak", 0.8, IF(L46="non existent", 1))))) -> 0.6 | N46: =J46*M46 -> 5.4 | O46: =IF(N46<=4,"Acceptable ",IF(N46<=14,"Moderalety Acceptable","Unacceptable")) -> Moderalety Acceptable | P46: =IF(N46<=4,"Low Risk",IF(N46<=14,"Medium Risk","High Risk")) -> Medium Risk | Q46: =IF(P46="High Risk","Treatment",IF(P46="Medium Risk","Treatment","Tolerate")) -> Treatment
H47: 3 | I47: 3 | J47: =H47*I47 -> 9 | L47: Satisfactory | M47: =IF(L47="very good", 0.2, IF(L47="good", 0.4, IF(L47="Satisfactory", 0.6, IF(L47="weak", 0.8, IF(L47="non existent", 1))))) -> 0.6 | N47: =J47*M47 -> 5.4 | O47: =IF(N47<=4,"Acceptable ",IF(N47<=14,"Moderalety Acceptable","Unacceptable")) -> Moderalety Acceptable | P47: =IF(N47<=4,"Low Risk",IF(N47<=14,"Medium Risk","High Risk")) -> Medium Risk | Q47: =IF(P47="High Risk","Treatment",IF(P47="Medium Risk","Treatment","Tolerate")) -> Treatment
H48: 3 | I48: 3 | J48: =H48*I48 -> 9 | L48: Satisfactory | M48: =IF(L48="very good", 0.2, IF(L48="good", 0.4, IF(L48="Satisfactory", 0.6, IF(L48="weak", 0.8, IF(L48="non existent", 1))))) -> 0.6 | N48: =J48*M48 -> 5.4 | O48: =IF(N48<=4,"Acceptable ",IF(N48<=14,"Moderalety Acceptable","Unacceptable")) -> Moderalety Acceptable | P48: =IF(N48<=4,"Low Risk",IF(N48<=14,"Medium Risk","High Risk")) -> Medium Risk | Q48: =IF(P48="High Risk","Treatment",IF(P48="Medium Risk","Treatment","Tolerate")) -> Treatment
... H57: 3 | I57: 3 | J57: =H57*I57 -> 9 | L57: Satisfactory | M57: =IF(L57="very good", 0.2, IF(L57="good", 0.4, IF(L57="Satisfactory", 0.6, IF(L57="weak", 0.8, IF(L57="non existent", 1))))) -> 0.6 | N57: =J57*M57 -> 5.4 | O57: =IF(N57<=4,"Acceptable ",IF(N57<=14,"Moderalety Acceptable","Unacceptable")) -> Moderalety Acceptable | P57: =IF(N57<=4,"Low Risk",IF(N57<=14,"Medium Risk","High Risk")) -> Medium Risk | Q57: =IF(P57="High Risk","Treatment",IF(P57="Medium Risk","Treatment","Tolerate")) -> Treatment

Sheet Monitoring Tool
A1: Chief Directorate | B1: Risk No. | C1: Risk Description | D1: Action to improve management of the risk | E1: Action Owner | F1: Timeline | G1: Current Status | H1: Reasons for deviation & recovery plan | I1: New Timeline | J1: Action in Quarter? | K1: Actions Completed? | L1: Residual Risk Value as at 30 June 2025
A2: CS | B2: CS-1 | C2: Inadequate management of performance by supervisors | D2: Continuous implementation of EPMDS quality control checklist | E2: Director HRD &OD | F2: Quarterly | G2: Quality control check list is part of the submission of PMDS documents. PMDS Unit does not accept documents without the quality control checklist. | H2: None | J2: Yes | K2: Completed
A3: CS | B3: CS-2 | C3: Incorrect record of Leave accruals | D3: The Risk has been tolerated in as far as the Risk Tolerance level, however risk is still managed. | E3: Director HRM | F3: Quarterly | G3: Top Management and SMS members were trained on eleave and currently using the system 15 May 2025. All other employees of the department used the e-leave system from the 01 September 2025. | H3: None | J3: Yes | K3: Completed
A4: CS | B4: CS-3 | C4: Default Judgements | D4: The Risk has been tolerated in as far as the Risk Tolerance level, however risk is still managed. | E4: Director : Legal | F4: Quarterly | G4: Still monitoring the existing controls for the first and second quarter, a new monitoring control will be implemented when the need arise in the third quarter. | J4: Yes | K4: Completed | L4: ='Register 2025-26'!V12 -> 0
A5: CS | B5: ICT-01 | C5: Inadequate management of Departmental records and knowledge | D5: Conduct awarenesses on records management | E5: Director:GICTM | F5: Quarterly | G5: An awareness session was conducted in collaboration with change management unit with the aim of introducing a new departmental records management system (MemoApp). | J5: Yes | K5: Completed
A6: CS | D6: Monitor the implementation of the records management policy | E6: Director:GICTM | F6: Quarterly | G6: All staff members were onboarded into a Mema-App system and some of the directorates' file plan has been reviewed and configured on the systems. The review of the file plan for other units is still on-going. All users were also training on the use of the systems. | J6: Yes | K6: Completed
A7: CS | D7: Digitise and automate records management | E7: Director:GICTM | F7: Quarterly | G7: The Memo App has been implemented to automate records management processes within the department. The implementation of this system will streamline records-keeping, improve efficiency and ensure that all departmental records are managed effectively. | J7: Yes | K7: Completed
A8: HSFP | B8: HSFP-1 | C8: Illegal occupation and use of houses | D8: Establishment and monitoring of Beneficiary Allocation Committees to ensure fairness in the allocation process and to avoid possible misallocation and wrongful occupation of houses | E8: Director: Beneficiary Management | F8: Quarterly | G8: BAC were established in the following municipalities: - Resuscitation of BAC in Sundays River LM, Beneficiary Correct Occupation (BCO) was done in the following Municipality: - Elundini Local Municipality phase 2 of the Ugie project. - Tracing of Missing Beneficiaries in Matatiele Local Municipality | J8: Yes | K8: Completed | L8: ='Register 2025-26'!V14 -> 0
A9: HSFP | D9: Provide support to Municipalities regarding Beneficiary Administration | E9: Director: Beneficiary Management | F9: Quarterly | G9: Beneficiary Allocation policy was conducted with Capacity Building in the following municipalities: - Ndlambe Local Municipality. | J9: Yes | K9: Completed
A10: HSFP | B10: HSFP-2 | C10: Inadequate implementation of facilitation interventions | D10: Implementation of the Social Facilitation Strategy | E10: Director: Social Facilitation and Customer Care | F10: Quarterly | G10: Social facilitation strategy has been implemented in various departmental projects during quarter under review where five (5) interventions were implemented to respond on social issues | J10: Yes | K10: Completed | L10: ='Register 2025-26'!V15 -> 0
A11: HSFP | B11: HSFP-3 | C11: Procurement of 40% MSMEs from the framework agreement may not be achieved. | D11: Acquire lists of MSME contractors appointed by the region who are utilizing 40% of the Human Settlements’ Conditional Grant | E11: Director: Emerging Contractor Development | F11: Quarterly | G11: List of MSMEs and the Category B contractors appointed from the Framework Agreement with between one and one hundred (01 - 100) units was acquired from the Directorate of Supply Chain Management and the regions. The list will be utilised to determine percentage of the amount paid to them relative to the Human Settlements Conditional Grant. | J11: Yes | K11: Completed | L11: ='Register 2025-26'!V16 -> 0
A12: HSFP | B12: HSFP-4 | C12: Inability for the department to provide input on skills development to unemployed youth (apprenticeship and learning ) | D12: Enhance working relationship with the Construction Education Training Authority (CETA) to receive funding permanently for funding the learnership and apprenticeship programmes. | E12: Director: Emerging Contractor Development | F12: Annually | G12: CETA funding for eighty (80) learnership opportunities successfully secured | H12: None | J12: No | L12: ='Register 2025-26'!V17 -> 0
A13: HSFP | D13: Allocation of funding from OPSAP | E13: Director: Emerging Contractor Development | F13: Annually | G13: R1.5 million has been approved for allocation from the OPSCAP to carry out the Apprenticeship programme. Through this fund, it is anticipated that the Directorate will be able to procure the training service provider, however, there has been a delay in the processing thereof. | H13: None | J13: No
A14: HSFP | B14: HSFP-5 | C14: Appointed contractors may not adequately report on the number of jobs created | D14: The Directorate of Emerging Contractors in cooperation with the Project Managers, EPWP Coordinators, Hands On Support and ECDPWI to collect compliant data from the appointed contractors | E14: Director: Emerging Contractor Development | F14: Quarterly | G14: Arising from the cooperation with the ECDPWI there has been an improvement in EPWP reporting. This cooperation resulted in the Department exceeding the National Department Public Works & Infrastructure half year target of five hundred by eighty eighty (88). The Department is on track to achieve the provincial target of five thousand eight hundred and thirty four (5 834). | J14: Yes | K14: Completed
A15: HSFP | D15: Prepare an EPWP compliance checklist template for sign off by Project Manager, EPWP coordinator and the Regional Director. | E15: Director: Emerging Contractor Development | F15: Quarterly | G15: EPWP Checklists was prepared and distributed to all Regional Directors. | J15: Yes | K15: Completed
A16: HSFP | D16: Acquire labour for employment in projects when and where required from the Department of Employment and Labour. | E16: Director: Emerging Contractor Development | F16: Quarterly | G16: There has been an agreement with the Department of Labour and Employment to access its database of unemployed personnel for the Departmental projects should the need arise. | J16: Yes | K16: Completed
A17: HSFP | B17: HSFP-6 | C17: Procurement of 10% building materials from black industrialists may not be achieved since there is no policy provision and provision in the contracts of the appointed contractors | D17: Conduct a survey amongst the contractors appointed in all Departmental Regions to determine percentage of Black Industrialists whose building materials is being procured by appointed contractor | E17: Director: Emerging Contractor Development | F17: 31/03/2025 | G17: on the 5th August 2025 the survey questionnaire was emailed to one hundred and thirty eight (138) contractors appointed by the Department to determine if they procure building materials from the Black Industrialists. To date six (06) contractors have responded. The Directorate will continue engaging contractors to cooperate in this regard. | J17: No | L17: ='Register 2025-26'!V19 -> 0
A18: HSFP | D18: Report on percentage of Black Industrialists whose building materials is procured by the contractors appointed | E18: Director: Emerging Contractor Development | F18: 31/03/2025 | G18: The report is dependent on the feedback from contractors relative to the procurement of the building material supplies from the Black Industrialists. | J18: No
A19: HSFP | D19: Recommend mechanisms for policy Implementation mechanism. | E19: Director: Emerging Contractor Development | F19: 31/03/2025 | G19: No recommendation at this stage | J19: No
A20: HSFP | B20: HSFP-7 | C20: Delays in the processes of project approval | D20: The Risk has been tolerated in as far as the Risk Tolerance level, however risk is still managed. | E20: Director: Beneficiary Management | F20: Quarterly | G20: The are no new projects submitted for the quarter. The appointment of the Assessment committees members is underway. The department is dealing with unblocking of blocked projects, the funding adjustments were done through the adhoc process for MEC approval. Currently there are no delays in the process. | J20: Yes | K20: Completed | L20: ='Register 2025-26'!V20 -> 0
A21: HSIP | B21: HSIP 1 | C21: Inadequate provision of temporary relief to emergency housing cases | D21: Engage and support relevant stakeholders on policy implementation | E21: Director: Emergency Housing and EPHP | F21: Quarterly | G21: There were no policy engagements as the accredited Municipalities are independently performing the Emergency Housing function and accessing funding directly from National Department of Human Settlements.Non- accredited Municipalities are able to perform functions associated with the provision of emergency housing programme by the Province. | H21: None | I21: N/A | J21: Yes | K21: Completed | L21: ='Register 2025-26'!V21 -> 0
A22: HSIP | B22: HSIP 2 | C22: Inconsistence in the implementation of the EPHP programme | D22: Conduct workshops for appointed CRO's to reinforce the understanding | E22: Director: Emergency Housing and EPHP | F22: Quarterly | G22: There were no new CRO's appointed hence no workshops conducted | H22: None | I22: N/A | J22: Yes | K22: Completed | L22: ='Register 2025-26'!V22 -> 0
A23: HSIP | D23: Engage stakeholders to align to the implementation of the EPHP | E23: Director: Emergency Housing and EPHP | F23: Quarterly | G23: The current projects under implementation are implemented in line with the policy hence no need for engagement of stakeholders | H23: None | I23: N/A | J23: Yes | K23: Completed
A24: HSIP | D24: Establishment of the CRO panel for capacity enhancement through SCM processes | E24: Director: Emergency Housing and EPHP | F24: 31/03/2026 | G24: Draft Terms of Reference in place | H24: None | I24: Fourth quarter | J24: No
A25: HSIP | B25: HSIP 3 | C25: Inability to upgrade informal settlements to the desired phases 1, 2 & 3 | D25: Review province wide upgrading strategy to align with DORA and the National Human Settlements upgrading framework | E25: Director: Informal Settlements Upgrading | F25: 30/09/2025 | G25: The department is reviewing the strategy for the MTDP following the reduction of the funding from National | H25: The department is awaiting clarity on outer years funding | I25: Next Quarter | J25: Yes | K25: Not Completed | L25: ='Register 2025-26'!V23 -> 0
A26: HSIP | D26: Strengthen partnerships with delivery stakeholders | E26: Director: Informal Settlements Upgrading | F26: Quarterly | G26: The internal partnerships have been strengthened with Land Acquisition, Social Facilitation and Regions. | H26: None | I26: N/A | J26: Yes | K26: Completed
A27: HSIP | D27: Enhance social facilitation and awareness | E27: Director: Informal Settlements Upgrading | F27: Quarterly | G27: The consolidated departmental social facilitation strategy is being implemented through the regional social facilitation to include the UISP. | H27: None | I27: N/A | J27: Yes | K27: Completed
A28: HSIP | D28: Enforcement of contractual terms and conditions | E28: Director: Informal Settlements Upgrading | F28: Quarterly | G28: All contracts have the terms of performance effectively enforced. | H28: None | I28: N/A | J28: Yes | K28: Completed
A29: HSPA | B29: HSPA- 01 | C29: Inadequate devolution of land parcels to municipalities | D29: Engage municipalities to provide council resolutions/regulations and or development plans inline with the land to be devolved | E29: Director: Land Acquisition and Tenure Services | F29: Quarterly | G29: Council resolutions provided | H29: No deviation | J29: Yes | K29: Completed | L29: ='Register 2025-26'!V24 -> 0
A30: HSPA | D30: Engage state attorney to ensure timeous appointment of correspondents | E30: Director: Land Acquisition and Tenure Services | F30: Quarterly | G30: Engagements are being done with the State Attorney | H30: No deviation | J30: Yes | K30: Completed
A31: HSPA | B31: HSPA- 02 | C31: Inadequate number of pre-1994 housing stock transferred to beneficiaries | D31: Provision of support to municipalities to ensure completeness of beneficiary list | E31: Director: Sales, Transfers and Assets | F31: Quarterly Quarterly Quarterly | G31: The following Municipalities were supported during the 2nd quarter and this culminated into compilation and submission of Beneficiary lists and signed deeds of sale for transfer and title deeds registration purposes: - BCMM - Enoch Mgijima LM | H31: No deviation | J31: Yes | K31: Completed | L31: ='Register 2025-26'!V25 -> 0
A32: HSPA | D32: Awareness on the acceptance of the stand | E32: Director: Sales, Transfers and Assets | F32: Quarterly | G32: Engagement sessions have been held with affected Regions and Municipalities on awareness drives pertaining to acceptance of stands. The Programme is awaiting submission of identified areas by Municipalities: - Chris Hani - Sarah Baartman | H32: No deviation | J32: Yes | K32: Completed
A33: HSPA | B33: HSPA- 03 | C33: Inadequate number of First Home Finance subsidies disbursed | D33: Continuous engagements with First Home Finance stakeholders | E33: Director:Social and Rental Housing Programme | F33: Quarterly | G33: Awareness engagements are conducted on a continuous basis and sessions were held with various stakeholders in conjunction with Capacity Building.A total of (5) different stakeholders were presented with FHF policy. | H33: No deviation | J33: Yes | K33: Completed | L33: ='Register 2025-26'!V26 -> 0
A34: HSPA | D34: Align budget to set targets | E34: Director:Social and Rental Housing Programme | F34: 30/09/2025 | G34: The plan was to against a planned target of (78) and we achieved (68). Under achievement by (10) disbursements. | H34: The deviation was as a result of late submission of outstanding documents (invoices) by conveyancers. | I34: Next Quarter | J34: Yes | K34: Not Completed
A35: HSPA | B35: HSPA- 04 | C35: Potential delays in resolving complex rental cases | D35: The Risk has been tolerated in as far as the Risk Tolerance level, however risk is still managed. | E35: Director:Social and Rental Housing Programme | F35: Quarterly | G35: Currently conducting pre hearing conference and inspection of rental dwellings.87 were resolved by tribunal through full hearing. | J35: Yes | K35: Completed | L35: ='Register 2025-26'!V27 -> 0
A36: FMS | B36: CFO-01 | C36: Non adherence to SCM processes and procedures | D36: Training of SCM practitioners and Bid Committee Members | E36: Director: SCM | F36: 31/12/2025 | G36: In quarter 2 no trainings were planned for SCM officials and Bid Committee members. Provincial Treasury will provide SCM And Bid Committee training in quarter 4 | J36: No | L36: ='Register 2025-26'!V28 -> 0
A37: FMS | D37: Standard Operating Procedures to be finalised and communicated | E37: Director: SCM | F37: 30/06/2025 | G37: The Standard Operating Procedures have been reviewed and communicated during quarter 1. Updating of the Standard Operating Procedures is ongoing due to the new circulars and Instruction notes issued by Provincial Treasury. | J37: No
A38: FMS | B38: CFO-02 | C38: Misuse of government vehicles | D38: Conduct awareness sessions on Fleet Management Policy | E38: Director : Asset Management | F38: Quarterly | G38: Awareness campaigns are conducted during asset verification and was done during the 2nd quarter. | J38: Yes | K38: Completed | L38: ='Register 2025-26'!V29 -> 0
A39: FMS | D39: Implement disciplinary processes as per departmental Fleet Management Policy | E39: Director : Asset Management | F39: Quarterly | G39: There were no incidents relating to misuse of state vehicles during the 2nd quarter. There were two incidents of hijacking of state vehicles in OR Tambo and 1 at Head Office during the 2nd quarter. | J39: Yes | K39: Completed
A40: FMS | D40: Review tracker reports and report on identified exceptions | E40: Director : Asset Management | F40: Quarterly | G40: There were no exceptions identified on the tracker reports during this period. | J40: Yes | K40: Completed
A41: FMS | B41: CFO-03 | C41: Loss of Assets and consumables | D41: Conduct awareness campaigns on asset management during asset verification. | E41: Director : Asset Management | F41: bi-annually | G41: Awareness campaigns were conducted during asset verification in quarter 2. | J41: Yes | K41: Completed | L41: ='Register 2025-26'!V30 -> 0
A42: FMS | D42: Issue out circular on asset management | E42: Director : Asset Management | F42: bi-annually | G42: A Circular on Safe Guarding of state No circulars was issued during this quarter | J42: No | K42: Completed
A43: FMS | D43: Timeous reporting of asset losses | E43: Director : Asset Management | F43: Quarterly | G43: 1 loss of an HP Laptop was reported during this quarter | J43: Yes | K43: Completed
A44: FMS | D44: Implementation of recommendations from investigations | E44: Director : Asset Management | F44: Quarterly | G44: No investigations on losses have been finalised | J44: Yes | K44: Completed
A45: FMS | B45: CFO-04 | C45: Failure to pay suppliers within 30 days | D45: Conduct awareness sessions for end users on proper processes for submission of invoices | E45: Director:FAS | F45: Quarterly | G45: Awareness sessions for end users on proper processes for submission of invoices was done in quarter 2. | J45: Yes | K45: Completed | L45: ='Register 2025-26'!V31 -> 0
A46: FMS | D46: Engage service providers on submission of invoices | E46: Director:FAS | F46: Monthly | G46: Engagement with service providers on timeous submission of invoices was done. | J46: Yes | K46: Completed
A47: FMS | B47: CFO-05 | C47: Inadequate pay point management | D47: The Risk has been tolerated in as far as the Risk Tolerance level, however risk is still managed. | E47: Director:FAS | F47: Quarterly | G47: The Paypoint Management Policy has been implemented. The policy is monitored on monthly basis | J47: Yes | K47: Completed | L47: ='Register 2025-26'!V32 -> 0
A48: FMS | B48: CFO-06 | C48: Inadequate implementation of Internal controls and transversal systems security measures | D48: Quarterly reports on weaknesses identified within policies and processes | E48: Director: Internal and Systems Control | F48: Quarterly Monthly | G48: Quarterly reports on weaknesses identified within policies and processes were submitted in quarter 2. | J48: Yes | K48: Completed | L48: ='Register 2025-26'!V33 -> 0
A49: FMS | D49: Monitoring of AIP action plans to address root causes of findings | E49: Director: Internal and Systems Control | F49: Monthly | G49: Monitoring of AIP action plans to address root causes of findings was done | J49: Yes | K49: Completed
A50: FMS | B50: CFO-07 | C50: Misstatement of annual financial statements | D50: Supporting schedules signed off as evidence of review by relevant Chief Directorates | E50: Director: Financial Management Accounting | F50: Quarterly | G50: Supporting schedules signed off as evidence of review by relevant Chief Directorates was done during this period. | J50: Yes | K50: Completed | L50: ='Register 2025-26'!V34 -> 0
A51: FMS | B51: CFO-08 | C51: Incomplete contract register | D51: Sourcing and implementation of Electronic contract management system | E51: Director: Contracts Management | F51: Quarterly | G51: The Enterprise Resourcing Planning system development has incorporated the Electronic Contract Management System | J51: Yes | K51: Completed | L51: ='Register 2025-26'!V35 -> 0
A52: FMS | D52: Verification of bid status report for awarded contracts and variation order register | E52: Director: Contracts Management | F52: Quarterly | G52: The bid status report for awarded contracts and variation order register were verified in quarter 2. | J52: Yes | K52: Completed
A53: FMS | B53: CFO-09 | C53: Inadequate budget allocation | D53: Communication of cost containment measures to all Staff | E53: Director: Financial Management Accounting | F53: 30/06/2025 | G53: The cost containment policy has been reviewed as per the new guidelines issued by National Treasury and communicated | J53: No | L53: ='Register 2025-26'!V36 -> 0
A54: FMS | D54: Review of S&T Policy to be aligned with cost containment measures | E54: Director: Financial Management Accounting | F54: Quarterly | G54: The S&T Policy is still being reviewed | J54: Yes | K54: Completed
A55: FMS | D55: Reporting of travel expenditure to responsible programme managers | E55: Director: Financial Management Accounting | F55: Quarterly | G55: Reporting and monitoring of travel expenditure is done through IYM | J55: Yes | K55: Completed
A56: HSDPP | B56: PPR-1 | C56: Fragmented planning between spheres of government leading to misalignment of plans | D56: Participation in IGR planning forums (National, Provincial and Municipal Infrastructure Planning Fora, Provincial Cluster Working Groups, District Development Model fora, IDP Fora other planning working streams). | E56: Director: Human Settlements Delivery Planning | F56: Quarterly | G56: Participation in the IDP assessment session assisting the Municipalities in the alignment of HSSPs with Municipal IDPs and SDFs | H56: None | J56: Yes | K56: Completed | L56: ='Register 2025-26'!V37 -> 0
A57: HSDPP | D57: Provide municipalities with technical support on development Human Settlements Sector Plans | E57: Director: Human Settlements Delivery Planning | F57: Quarterly | G57: 20 draft HSSPs were developed and 6 have been presented and endorsed by Municipal Councils | H57: None | J57: Yes | K57: Completed
A58: HSDPP | D58: Development of the Human Settlements Development Grant (HSDG) and Informal Settlements Upgrading Partnership Grant (ISUPG) Business Plans | E58: Director: Human Settlements Delivery Planning | F58: 46061 | G58: Draft HSDG and ISUPG Business Plan for 2026/27 submitted and is aligned with IDPs | H58: None | J58: No
A59: HSDPP | B59: PPR-2 | C59: Inadequate capacity building and support to Municipalities to perform Human Settlements functions | D59: Advocacy and Consultation through capacity building workshops with the external stakeholders | E59: Director: Capacity Building and Municipal Support | F59: Quarterly | G59: Capacitated Municipalities on the following programmes i.e. Housing Needs Register, Accreditation Programme, Social and Rental Housing, Destitute and Vulnerable Groups, Beneficiary Management Policy, Beneficiary Correct Occupation, Project application process, (ISBT) innovative sustainable building technology, Social Facilitation and Customer Care, Emergency Housing. Supported KSD and Sundays River on the establishment of allocations committee | H59: None | J59: Yes | K59: Completed | L59: ='Register 2025-26'!V38 -> 0
A60: HSDPP | D60: Provide support towards accreditation of new Municipalities and Monitoring the performance of accredited municipalities | E60: Director: Capacity Building and Municipal Support | F60: Quarterly | G60: Post-Accreditation support provided to BCMM and NMBM regarding programme implementation and quarterly reporting Pre- accreditation support provided to Enoch Mgijima, Matatile, Umzimvumbu and Kouga LM for the reviewal of HSSPs and the development of Accreditation Business Plan Pre- assessment for Kouga and KSD LM has been conducted and feedback provided. | H60: None | J60: Yes | K60: Completed
A61: HSDPP | D61: Enhance the functioning of the National Housing Needs Register | E61: Director: Capacity Building and Municipal Support | F61: Quarterly | G61: Providing hand on support through ILIMA campaign and awareness held for Nyandeni, Ngqushwa and Mhlontlo Local Municipalities NHNR and HSS systems training conducted for 4 Municipalities. Resuscitation of the Beneficiary Allocations Committee for Sundays River and KSD Local Municipalities. | H61: None | J61: Yes | K61: Completed
A62: HSDPP | D62: Implementation of Short learning programs as per Service Level Agreement with Institution of Higher Learning to capacitate municipalities | E62: Director: Capacity Building and Municipal Support | F62: 30/09/2025 | G62: Two Short Learning Programmes conducted for Councillors and Traditional Leaders on the 22-27 September 2025 as follows: Informal Settlements Upgrading and Theories and Managing Public Participation in Human Settlements Delivery. | H62: None | J62: Yes | K62: Completed
A63: HSDPP | D63: Develop a capacity building plan | E63: Director: Capacity Building and Municipal Support | F63: 31/03/2025 | J63: No
A64: HSDPP | B64: PPR-3 | C64: Non adherence to policies and guidelines | D64: Conduct policy roll out, interpretation and refresher workshops | E64: Director: Human Settlements Research and Policy Development | F64: Annually | G64: The department rolled out Beneficiary Management and Title Deeds Policies to 8 municipalities to empower Political Leaders and Municipal Officials. | H64: None | J64: Yes | K64: Completed | L64: ='Register 2025-26'!V39 -> 0
A65: HSDPP | B65: PPR-4 | C65: Limited use of research findings and recommendations in human settlements development activities | D65: Dissemination of research findings through different platforms such as round table discussions, IGR meetings, DDMs, Human Settlements Forums and human settlements conferences. | E65: Director: Human Settlements Research and Policy Development | F65: Quarterly | G65: Dissemination of study findings and recommendations on "Assessing living conditions of communities where government subsidised houses were constructed with Asbestos Materials in the Eastern Cape Province", and " A study assessing conditions of mud houses in Rural and Urban space of the Eastern Cape", were done internally and in 2 Municipalities. | H65: None | J65: Yes | K65: Completed | L65: ='Register 2025-26'!V40 -> 0
A66: HSDPP | D66: Implementation of research and dissemination Framework | E66: Director: Human Settlements Research and Policy Development | F66: Quarterly | G66: Research studies were dissemination various forum accordance with dissemination framework | H66: None | J66: Yes | K66: Completed
A67: DC&PM | B67: DCPM 1 | C67: Inadequate support to the implementation of Human Settlements Projects | D67: Develop ISBT framework agreement | E67: Chief Director: District Coordination and Project Management | F67: 31/12/2025 | G67: A procurement strategy and Terms of reference for the framework have been developed. And have included framework in the mid-term adjustment of the procurement plan. | J67: No | L67: ='Register 2025-26'!V41 -> 0
A68: DC&PM | D68: Effective participation in Municipal IGR Forums to ensure resolution to bulk infrastructure challenges | E68: Chief Director: District Coordination and Project Management | F68: Quarterly | G68: Regions attend IGR Forums, MMC forum, Executive mayoral forums and cluster forums in their respective regions and bulk infrastructure challenges are being attended to and resolved in the IGR forums. | J68: Yes | K68: Completed
A69: DC&PM | B69: DCPM 2 | C69: Inability to pay contractors within 30 days | D69: Spreading out of the project scope over three years | E69: Chief Director: District Coordination and Project Management | F69: Quarterly | G69: The framework agreement is in place to address spreading out of project scope over three years, | J69: Yes | K69: Completed | L69: ='Register 2025-26'!V42 -> 0
A70: DC&PM | D70: Phasing of the projects into manageable scope of works ( magnitude or size of the projects) | E70: Chief Director: District Coordination and Project Management | F70: Quarterly | G70: The Frame work agreement is being utilised to address issues of phasing of the projects into manageable scope of works. After the department issued a letter notifying OR Tambo District Mun they have submitted a response and the dep is busy with consideration of their response which will be followed by an addendum. | J70: Yes | K70: Completed
A71: DC&PM | D71: Termination of non preforming contractors | E71: Chief Director: District Coordination and Project Management | F71: Quarterly | G71: Termination letter for the Mzimvubu Municipality for all projects that are not moving. | J71: Yes | K71: Completed
A72: DC&PM | D72: Effective financial management to ensure claims are aligned with budget allocation | E72: Chief Director: District Coordination and Project Management | F72: Quarterly | G72: The programme is effectively managing and ensuring that claims spend according to the budget allocation. | J72: Yes | K72: Completed
A73: DC&PM | D73: Conduct awareness on CSD issues and changing of banking details during regional and contractor sessions | E73: Chief Director: District Coordination and Project Management | F73: Quarterly | G73: The Contractors are engaged through regional and provincial contractor meetings about CSD issues and changing of banking details. | J73: Yes | K73: Completed
A74: DC&PM | B74: DCPM 3 | C74: Rectification backlog | D74: Strict implementation of Rectification Guidelines | E74: Director: PMU | F74: Quarterly | G74: Projects are being implemented as per the 10% directive which is a National guideline, | J74: Yes | K74: Completed | L74: ='Register 2025-26'!V43 -> 0
A75: DC&PM | D75: Monitoring and control of expenditure patterns against directive (10%) | E75: Director: PMU | F75: Quarterly | G75: The programme is monitoring and ensuring that projects are spending within the allocation. | J75: Yes | K75: Completed
A76: DC&PM | D76: Efficient and effective Project Management on rectification | E76: Director: PMU | F76: Quarterly | G76: the programme is efficiently and effectively applying Project Management and National guidelines on rectification. | J76: Yes | K76: Completed
A77: DC&PM | D77: Motivate for special funding outside HSDG | E77: Director: PMU | F77: 30/09/2025 | G77: A letter has been submitted to the National Department of Human Settlements requesting an increase in the rectification funding allocation from 10% to 30% of the overall Human Settlements Grant Allocation. The Department is currently awaiting a response from the National Department. | H77: The deviation is due to the pending response from the National Department of Human Settlements on the Department’s request to adjust the rectification funding allocation from 10% to 30% of the total Grant. | I77: 30/03/2026 | J77: Yes | K77: Not Completed
A78: S&S | B78: SM-01 | C78: Inadequate Communication support services | D78: Working with Housing Institutions to enhance advocacy programs | E78: Director: Communication Management | F78: Quarterly | G78: Collaborated with NHBRC for information stalls during the launch of the Youth Artisan Development Project in BCMM on 22August 2025. | H78: None | J78: Yes | K78: Completed | L78: ='Register 2025-26'!V44 -> 0
A79: S&S | D79: Increasing the departmental social media platforms | E79: Director: Communication Management | F79: Quarterly | G79: Strengthened the department’s social media platforms by developing and executing structured weekly content plans. This strategy proved effective, resulting in significant growth in followers and views—reaching thousands—and ensuring our messaging effectively reached the targeted audience. Content shared included project profiles, youth development initiatives, flood relief efforts, information on subsidies and programmes, as well as updates on title deeds and the rental tribunal. | H79: None | J79: Yes | K79: Completed
A80: S&S | D80: Sharing of resources within the Ministry | E80: Director: Communication Management | F80: Quarterly | G80: Collaborated with the National Department of Human Settlements by sharing content and equipment during site visits to flood-affected areas in OR Tambo and Amathole. | H80: None | J80: Yes | K80: Completed
A81: S&S | B81: SM-02 | C81: Inaccurate and incomplete performance information reporting | D81: Conduct follow up of analysis report | E81: Director: Institutional Performance Assessment and Programme Evaluation | F81: Quarterly | G81: The analysis of the uploaded PoE for the Quarter 1 performance report was conducted and POE analysis report produced. The follow up with Directorates that had findings was also conducted and corrections were made where required. | H81: None | J81: Yes | K81: Completed | L81: ='Register 2025-26'!V45 -> 0
A82: S&S | D82: Conduct backend audit ( Prog 2,3 & 4) | E82: Director: Institutional Performance Assessment and Programme Evaluation | F82: Bi Annual | G82: The Back-end Audit for Programmes, 2, 3, and 4 will be conducted during the third quarter, and the report will be produced and shared with relevant directotates for the implementation of recommendations. | H82: None | J82: No
A83: S&S | B83: SM-03 | C83: Non compliance with strategic planning time frames | D83: An action plan with an itinerary will be circulated in line with the provincial treasury planning budget process. | E83: Director: Strategic Planning | F83: 30/07/2025 | G83: An itinerary for the one on one strategic sessions with programmes has been developed and circulated to programme managers dated 12/08/2025 | H83: None | J83: Yes | K83: Completed | L83: ='Register 2025-26'!V46 -> 0
A84: S&S | D84: Conduct trainings sessions on the revised strategic plan and annual performance plan framework with programmes through Macro and Micro one on one strategic planning sessions | E84: Director: Strategic Planning | F84: 30/09/2025 | G84: One on One working sessions was held from 27 August – 26 September 2025 to review performance indicators and TID's in preparation of the first draft Annual Performance Plan 2026/27 | H84: None | J84: Yes | K84: Completed
A85: S&S | B85: SM-04 | C85: Inconsistent stakeholder participation in integrated Human Settlements delivery | D85: Implementation of the stakeholder engagement and IGR action plan | E85: Director: Stakeholder Engagement | F85: Quarterly | G85: 5 Stakeholder Engagements were coordinated - Eastern Cape All of Society Engagement New Urban Agenda Report,Launch of the Human Settlements Short Learning Programme and Agricultural Open Day. 2 House Handovers. 11 IGR Forums were supported:1 IGR Provincial forum and 10 Municipal IGR. | J85: Yes | K85: Completed | L85: ='Register 2025-26'!V47 -> 0
A86: S&S | D86: Co-ordinate MEC (Member of the Executive Council) and MMC (Member of the Municipal Council) engagements | E86: Director: Stakeholder Engagement | F86: Quarterly | G86: Due to competing priorities within the Ministry, the MMCs did not sit in Quarter 2. | H86: Awaiting for guidance in terms of prioritizations from the Ministry(OMEC) | I86: Next Quarter | J86: Yes | K86: Not Completed
H89: Completed | J89: =COUNTIF(K2:$K$86,H89) -> 68 | K89: =+J89/$J$92 -> 0.94444444 | L89: =+K89/$J$92 -> 0.013117284
H90: Partially Complete | J90: =COUNTIF(K2:$K$86,H90) -> 0 | K90: =+J90/$J$92 -> 0
H91: Not Completed | J91: =COUNTIF(K3:$K$86,H91) -> 4 | K91: =+J91/$J$92 -> 0.055555556
H92: Total | J92: =SUM(J89:J91) -> 72
H94: Completed
H95: Not Completed

Sheet Fraud Risk Register 
A1: Link to Outcome | B1: Risk number | C1: Chief Directorate | D1: Sub-Directorate | E1: Risk Category | F1: Risk Name | G1: Risk Description | H1: Risk Causes | I1: Consequences | J1: Impact Value (1-5) | K1: Likelihood Value (1-5) | L1: Inherent Risk Value | M1: Current controls | N1: Control Effectiveness | O1: Effectiveness rating | P1: Residual Risk Value | Q1: Risk Appetite | R1: Risk Tolerance | S1: Risk Response Treatment | T1: Risk Owner | U1: Action to improve management of the risk | V1: Action owner | W1: Timeline | X1: Current Status
A2: To manage human resource services | B2: CS1 | C2: Corporate Services | D2: HRP & HRAS | E2: Fraud and Corruption | F2: Misrepresentation by applicants | G2: Submission of falsified Curriculum Vitae (s) | H2: Lack of integrity on candidates Desperation to attain employment | I2: Appointment of incompetent officials Compromised service delivery | J2: 3 | K2: 4 | L2: =J2*K2 -> 12 | M2: Advert Z83 Reference Checking Personal suitability checks SAQA Verification Recruitment Policy Attraction and Retention Strategy Approved Annual Recruitment Plan Disciplinary Code and Procedure . | N2: good | O2: =IF(N2="very good", 0.2, IF(N2="good", 0.4, IF(N2="Satisfactory", 0.6, IF(N2="weak", 0.8, IF(N2="non existent", 1))))) -> 0.4 | P2: =L2*O2 -> 4.8 | Q2: =IF(P2<=4,R1"Acceptable ",IF(P2<=14,"Moderalety AcceptableU1","Unacceptable")) -> #VALUE! | R2: =IF(P2<=4,"Low Risk",IF(P2<=14,"Medium Risk","High Risk")) -> Medium Risk | S2: =IF(R2="High Risk","Treatment",IF(R2="Medium Risk","Treatment","Tolerate")) -> Treatment | T2: Chief Director: Corporate Services | U2: Verifying registrations with professional Councils Collaborate with Anti Fraud and Corruption during awareness sessions | V2: Director: Human Resource Management | W2: Quartely Quartely
A3: Empowered and integrated sustainable communities | B3: HSFP 2 | C3: Human Settlements Facilitation Programme | D3: Beneficiary Management | E3: Fraud and Corruption | F3: Fraudulent allocation of RDP houses | G3: Manipulation of beneficiary list (s) for allocation of RDP houses to non qualifying persons. ie Un-approved and approved lists. | H3: Changing of political leadership in Municipal Councils. Replacement of beneficiaries without their consent ie: Death, outstanding beneficiary documentation, beneficiaries who fail Housing Subsidy System (HSS) searches. Invasion of completed housing units by unlawful beneficiaries. | I3: Delay in service delivery, blocked and halted projects Social unrest Illegal occupation | J3: 3 | K3: 4 | L3: =J3*K3 -> 12 | M3: Housing code Beneficiary Housing Allocation policy. Housing needs register. Beneficiary Housing Allocation Committee. Housing Subsidy System. Acute Destitute Strategy. | N3: satisfactory | O3: =IF(N3="very good", 0.2, IF(N3="good", 0.4, IF(N3="Satisfactory", 0.6, IF(N3="weak", 0.8, IF(N3="non existent", 1))))) -> 0.6 | P3: =L3*O3 -> 7.2 | Q3: =IF(P3<=4,"Acceptable ",IF(P3<=14,"Moderalety Acceptable","Unacceptable")) -> Moderalety Acceptable | R3: =IF(P3<=4,"Low Risk",IF(P3<=14,"Medium Risk","High Risk")) -> Medium Risk | S3: =IF(R3="High Risk","Treatment",IF(R3="Medium Risk","Treatment","Tolerate")) -> Treatment | T3: Chief Director: Human Settlements Facilitation | U3: Facilitate and support the establishment and functionality of Beneficiary Allocation Committees (BACs) in Municipalities. To develop illegal occupation framework Support to Municipalities regarding Beneficiary Administration in following areas in the following beneficiciary allocation , policy advocate Review of the Service Delivery Model (SDM) | V3: Director: Beneficiary Management & Corporate Secretariat | W3: Quarterly Half -year Quarterly
A4: Empowered and integrated sustainable communities | B4: HSFP 3 | C4: Human Settlements Facilitation Programme | D4: Social Facilitation and Customer Care | E4: Fraud and Corruption | F4: Illegal selling and renting of RDP houses | G4: Illegal selling of RDP houses and rent-out before beneficiary before minimum period of 8 years of ownership of the property . | H4: Lack of prosecution for those illegal acts. Weak of control to manged the Illegal renting and selling of RDP houses Beneficiary upgraded their lives therefore no longer in need of RDP houses Lack of Knowledge on 8 year rule regarding the selling RDP house. | I4: Prolong the housing backlog by selling houses at a price below the market value, and then returning to live in informal settlements. Occupying them illegally as no title deeds were issued Illegal profit / money making scheme | J4: 3 | K4: 4 | L4: =J4*K4 -> 12 | M4: Section 10A and 10B of the National Housing Amendment Act 4 of 2001 restricts the voluntary selling of Government-subsidised houses. | N4: satisfactory | O4: =IF(N4="very good", 0.2, IF(N4="good", 0.4, IF(N4="Satisfactory", 0.6, IF(N4="weak", 0.8, IF(N4="non existent", 1))))) -> 0.6 | P4: =L4*O4 -> 7.2 | Q4: =IF(P4<=4,"Acceptable ",IF(P4<=14,"Moderalety Acceptable","Unacceptable")) -> Moderalety Acceptable | R4: =IF(P4<=4,"Low Risk",IF(P4<=14,"Medium Risk","High Risk")) -> Medium Risk | S4: =IF(R4="High Risk","Treatment",IF(R4="Medium Risk","Treatment","Tolerate")) -> Treatment | T4: Chief Director: Human Settlements Facilitation | U4: Awareness on the pre-emptive clause regarding the conditions contained in the sale agreement and title deed, a beneficiary shall not rent his/her property until the transfer of the property has been registered | V4: Director: Social Facilitation and Customer Care | W4: Ongoing
A5: Empowered and integrated sustainable communities | B5: HSFP 4 | C5: Human Settlements Facilitation Programme | D5: Social Facilitation and Customer Care | E5: Fraud and Corruption | F5: Bribery and corruption | G5: Bribery of Community Liason Officer(s) for employment of cheap labour and foreign employees. Manipulation of Project Steering Committee (PSC) by Councillor(s), Clo(s) and Contractors Prioritisation of un-approved beneficiaries on projects and manipulation of community employee lists | H5: Maximise profits Personal financial gain Missing beneficiaries Non adherence to applicable processes on replacements of beneficiaries None compensation of PSC members Non adherence to recruitment guidelines for local beneficiation. | I5: Social unrest Slow progress on site Halted and blocked projects Social unrest Slow progress on site Halted and blocked projects Poor quality of projects | J5: 4 | K5: 3 | L5: =J5*K5 -> 12 | M5: Housing Code Training of Project Steering Committees Housing Subsidy System (HSS) Housing Code Expanded Public Works Programe (EPWP) recruitment guidelines Technical site meetings PSC meetings | N5: Weak | O5: =IF(N5="very good", 0.2, IF(N5="good", 0.4, IF(N5="Satisfactory", 0.6, IF(N5="weak", 0.8, IF(N5="non existent", 1))))) -> 0.8 | P5: =L5*O5 -> 9.6 | Q5: =IF(P5<=4,"Acceptable ",IF(P5<=14,"Moderalety Acceptable","Unacceptable")) -> Moderalety Acceptable | R5: =IF(P5<=4,"Low Risk",IF(P5<=14,"Medium Risk","High Risk")) -> Medium Risk | S5: =IF(R5="High Risk","Treatment",IF(R5="Medium Risk","Treatment","Tolerate")) -> Treatment | T5: Chief Director: Human Settlements Facilitation | U5: Development of the Social Facilitation Strategy | V5: Director: Social Facilitation and Customer Care | W5: Second Quarter
A6: Empowered and integrated sustainable communities | B6: HSFP 5 | C6: Human Settlements Facilitation Programme | D6: Emerging Contractor Development | E6: Fraud and Corruption | F6: Bribery and corruption | G6: Possible manipulation of the Emerging contractors list to benefit towards the 30% subcontractors | H6: Unethical Behaviour Pressure to deliver on targets. Non-aderence to applicable policies Ineffective Internal controls Financial gain Missing information for contractors submitted for 30% emerging contractors beneficiation | I6: Delay in service delivery, blocked and halted projects Poor quality on projects | J6: 3 | K6: 3 | L6: =J6*K6 -> 9 | M6: Provincial Local Economic Development Framework (LED) Emerging contractror development policy | N6: satisfactory | O6: =IF(N6="very good", 0.2, IF(N6="good", 0.4, IF(N6="Satisfactory", 0.6, IF(N6="weak", 0.8, IF(N6="non existent", 1))))) -> 0.6 | P6: =L6*O6 -> 5.4 | Q6: =IF(P6<=4,"Acceptable ",IF(P6<=14,"Moderalety Acceptable","Unacceptable")) -> Moderalety Acceptable | R6: =IF(P6<=4,"Low Risk",IF(P6<=14,"Medium Risk","High Risk")) -> Medium Risk | S6: =IF(R6="High Risk","Treatment",IF(R6="Medium Risk","Treatment","Tolerate")) -> Treatment | T6: Chief Director: Human Settlements Facilitation | U6: Review the emerging contractors policy Develop the standard operating procedure | V6: Director: Emerging Contractor Development | W6: Second Quarter
A7: Good Governance | B7: S&S 6 | C7: Strategy and System | D7: Institutional Performance Assessment and Programme Evaluation | E7: Fraud and Corruption | F7: Misrepresentation of performance information by sub- programs | G7: Misrepresentation by business units that certain targets/milestones etc. have been achieved | H7: Lack of verification Inadequate controls Pressure to achieve targets and spend budget | I7: Reputational damage Negative audit outcomes Financial Misconduct | J7: 5 | K7: 4 | L7: =J7*K7 -> 20 | M7: Signed business processes are in place. Evidence based reports (OPMS) Portfolio of evidence files from sub-programs Physical verification | N7: Satisfactory | O7: =IF(N7="very good", 0.2, IF(N7="good", 0.4, IF(N7="Satisfactory", 0.6, IF(N7="weak", 0.8, IF(N7="non existent", 1))))) -> 0.6 | P7: =L7*O7 -> 12 | Q7: =IF(P7<=4,"Acceptable ",IF(P7<=14,"Moderalety Acceptable","Unacceptable")) -> Moderalety Acceptable | R7: =IF(P7<=4,"Low Risk",IF(P7<=14,"Medium Risk","High Risk")) -> Medium Risk | S7: =IF(R7="High Risk","Treatment",IF(R7="Medium Risk","Treatment","Tolerate")) -> Treatment | T7: Chief Director: Strategy and Systems | U7: Portfolio of evidence analysis reports Conduct back end audit for program 3 and 4 | V7: Director IPAPE | W7: Quarterly Bi- annual
A8: Good Governance | B8: S&S 7 | C8: Strategy and System | D8: Communication Management | E8: Fraud and Corruption | F8: Fraudulent use of Departmental corporate identity | G8: Unauthorised use of departmental corporate identity and communication platforms | H8: Accessibility of departmental corporate identity Hacking of departmental and linked social media platforms | I8: Misrepresentation of the department Reputational damage Misinformed communities | J8: 4 | K8: 5 | L8: =J8*K8 -> 20 | M8: Provincial communication strategy and policy Government Communication and Information System Guidelines (GCIS) Branding manual | N8: Good | O8: =IF(N8="very good", 0.2, IF(N8="good", 0.4, IF(N8="Satisfactory", 0.6, IF(N8="weak", 0.8, IF(N8="non existent", 1))))) -> 0.4 | P8: =L8*O8 -> 8 | Q8: =IF(P8<=4,"Acceptable ",IF(P8<=14,"Moderalety Acceptable","Unacceptable")) -> Moderalety Acceptable | R8: =IF(P8<=4,"Low Risk",IF(P8<=14,"Medium Risk","High Risk")) -> Medium Risk | S8: =IF(R8="High Risk","Treatment",IF(R8="Medium Risk","Treatment","Tolerate")) -> Treatment | T8: Chief Director: Strategy and Systems | U8: Finalisation of departmental communication strategy Review of the branding manual Conducting awareness campaigns | V8: Director: Communication Management | W8: Quarter 2 Quarter 2 Quarter 3 & 4
A9: Good Governance | B9: S&S 8 | C9: Strategy and System | D9: Government Information and Communication Technology Management (GICTM) | E9: Fraud and Corruption | F9: Misuse of ICT Systems by Unauthorised Threat actors (Misuse of passwords/ password sharing , Abuse of passwords and abuse of Departmental Systems) | G9: Unauthorised access to departmental systems by threat actors (hackers) | H9: Weak IT controls Obsolete Infrastructure Sharing of passwords | I9: Financial loss Data breach Misuse of IT systems Cyber attack | J9: 5 | K9: 5 | L9: =J9*K9 -> 25 | M9: IT security policy in place Network security devices in place Security reviews conducted quarterly Patch management system Cyber security awareness | N9: Satisfactory | O9: =IF(N9="very good", 0.2, IF(N9="good", 0.4, IF(N9="Satisfactory", 0.6, IF(N9="weak", 0.8, IF(N9="non existent", 1))))) -> 0.6 | P9: =L9*O9 -> 15 | Q9: =IF(P9<=4,"Acceptable ",IF(P9<=14,"Moderalety Acceptable","Unacceptable")) -> Unacceptable | R9: =IF(P9<=4,"Low Risk",IF(P9<=14,"Medium Risk","High Risk")) -> High Risk | S9: =IF(R9="High Risk","Treatment",IF(R9="Medium Risk","Treatment","Tolerate")) -> Treatment | T9: Chief Director: Strategy and Systems | U9: Submission for resourcing of ICT Develop ICT digital strategy Conduct ICT policy awareness | V9: Director:Government Information and Communication Technology Management (GICTM) | W9: End of Quarter 1 Quarter 3 Quarterly
A10: Good Governance | B10: S&S 9 | C10: Strategy and System | D10: IGR Stakeholder Engagement and IGR | E10: Fraud and Corruption | F10: Unauthorised Disclosing of information | G10: Inappropriate engagement of stakeholders | H10: Inadequate controls No guidelines on engagement of stakeholders | I10: Misappropriation of stakeholder donations Uncoordinated stakeholder engagements | J10: 3 | K10: 3 | L10: =J10*K10 -> 9 | M10: Stakeholder engagement and IGR Strategy in place Business process is in place | N10: good | O10: =IF(N10="very good", 0.2, IF(N10="good", 0.4, IF(N10="Satisfactory", 0.6, IF(N10="weak", 0.8, IF(N10="non existent", 1))))) -> 0.4 | P10: =L10*O10 -> 3.6 | Q10: =IF(P10<=4,"Acceptable ",IF(P10<=14,"Moderalety Acceptable","Unacceptable")) -> Acceptable | R10: =IF(P10<=4,"Low Risk",IF(P10<=14,"Medium Risk","High Risk")) -> Low Risk | S10: =IF(R10="High Risk","Treatment",IF(R10="Medium Risk","Treatment","Tolerate")) -> Tolerate | T10: Chief Director: Strategy and Systems | U10: Develop guidelines for stakeholder engagement | V10: Director Stakeholder Engagement | W10: 44926
A11: Security of land tenure and affordable residential and rental services | B11: HSPA 10 | C11: Human Settlements Property and Assets | D11: Sales, Transfers & Assets | E11: Fraud and Corruption | F11: Fraudulent Claims | G11: Manipulation of occupation of pre- 1994 old houses and sites Fraudulent Title deeds | H11: Unreliable registers from municipalities Lack of physical verification Evasiveness by illegal occupants Non-cooperation by departing tenants Non qualifying rental applicants that have previously benefited | I11: Transfer of pre-1994 old houses and sites to wrong beneficiaries. Inadequate revenue collection Fruitless and wasteful expenditure | J11: 3 | K11: 3 | L11: =J11*K11 -> 9 | M11: Physical verification in community halls Conveyancers report Enhanced Extended Discount Benefit Scheme (EEDBS) Rental agreement | N11: Satisfactory | O11: =IF(N11="very good", 0.2, IF(N11="good", 0.4, IF(N11="Satisfactory", 0.6, IF(N11="weak", 0.8, IF(N11="non existent", 1))))) -> 0.6 | P11: =L11*O11 -> 5.4 | Q11: =IF(P11<=4,"Acceptable ",IF(P11<=14,"Moderalety Acceptable","Unacceptable")) -> Moderalety Acceptable | R11: =IF(P11<=4,"Low Risk",IF(P11<=14,"Medium Risk","High Risk")) -> Medium Risk | S11: =IF(R11="High Risk","Treatment",IF(R11="Medium Risk","Treatment","Tolerate")) -> Treatment | T11: Chief Director: Human Settlements Property and Assets | U11: Conduct beneficiary verification Conduct social facilitation to qualifying beneficiaries to accept transfers of land Issue notices of eviction | V11: Director : Sale and Transfers | W11: Quarterly
A12: Security of land tenure and affordable residential and rental services | B12: HSPA 11 | C12: Human Settlements Property and Assets | D12: Social and Rental Housing | E12: Fraud and Corruption | F12: Fraudulent Payments | G12: Payment of false claims on value created | H12: Lack of verification process | I12: Overpayment/Financial Loss | J12: 4 | K12: 4 | L12: =J12*K12 -> 16 | M12: Standard operating procedure in place Physical verification on site | N12: Satisfactory | O12: =IF(N12="very good", 0.2, IF(N12="good", 0.4, IF(N12="Satisfactory", 0.6, IF(N12="weak", 0.8, IF(N12="non existent", 1))))) -> 0.6 | P12: =L12*O12 -> 9.6 | Q12: =IF(P12<=4,"Acceptable ",IF(P12<=14,"Moderalety Acceptable","Unacceptable")) -> Moderalety Acceptable | R12: =IF(P12<=4,"Low Risk",IF(P12<=14,"Medium Risk","High Risk")) -> Medium Risk | S12: =IF(R12="High Risk","Treatment",IF(R12="Medium Risk","Treatment","Tolerate")) -> Treatment | T12: Chief Director: Human Settlements Property and Assets | U12: Updating the Standard Operating Procedure | V12: Director: Land Acquisition & Tenure Services | W12: Quarterly
A13: Good Governance | B13: FMS 12 | C13: Financial Management Services | D13: Sub Directorate: Supply Chain Management (Demand and Acquisition Management) | E13: Fraud and Corruption | F13: Procurement Fraud | G13: Manipulation of procurement processes to favour specific bidder(s)/supplier(s). | H13: Interest on awarding a service provider. Collusion service providers/officials. Officials getting kickbacks for leaking the information. Non adherence to policies. | I13: Financial loss Adverse Audit Opinion | J13: 3 | K13: 4 | L13: =J13*K13 -> 12 | M13: Central Supplier Database, SBD 4 Signed declaration forms and oath pf secrecy by committee members Supply Chain Management Policy (SCM) | N13: Satisfactory | O13: =IF(N13="very good", 0.2, IF(N13="good", 0.4, IF(N13="Satisfactory", 0.6, IF(N13="weak", 0.8, IF(N13="non existent", 1))))) -> 0.6 | P13: =L13*O13 -> 7.2 | Q13: =IF(P13<=4,"Acceptable ",IF(P13<=14,"Moderalety Acceptable","Unacceptable")) -> Moderalety Acceptable | S13: =IF(R13="High Risk","Treatment",IF(R13="Medium Risk","Treatment","Tolerate")) -> Tolerate | T13: Chief Director: Financial Management Services | U13: Conduct continuous trainings of SCM officials and Bid committee members Request bid committee members and SCM officials to attend the compulsory online ethics management course Conduct BCSA training | V13: Director: Supply Chain Management | W13: Ongoing
A14: Good Governance | B14: FMS 13 | C14: Financial Management Services | D14: Sub Directorate: Asset Management | E14: Fraud and Corruption | F14: Misuse of government vehicles & Fuel card fraud | G14: Fraudulent use of government vehicles & fuel cards for private purposes. | H14: Non-adherence to policies and procedures Collusion with third parties Lack of enforcement of disciplinary action for non-compliance Inadequate approval process for vehicles usage Lack of management oversight over usage of company vehicles Picking up hitch hikers for financial gain | I14: Financial loss - excessive fuel charges Negative reputation | J14: 3 | K14: 4 | L14: =J14*K14 -> 12 | M14: Fleet Management Policy Authorised trip sheets Vehicle Inspections Monthly returns Tracker report from GFMS Personalised Vehicle Tags Awareness campaigns to all department officials and drivers. Spend Limit on the Fuel card Reconciliation of fuel expenditure. | N14: satisfactory | O14: =IF(N14="very good", 0.2, IF(N14="good", 0.4, IF(N14="Satisfactory", 0.6, IF(N14="weak", 0.8, IF(N14="non existent", 1))))) -> 0.6 | P14: =L14*O14 -> 7.2 | Q14: =IF(P14<=4,"Acceptable ",IF(P14<=14,"Moderalety Acceptable","Unacceptable")) -> Moderalety Acceptable | R14: =IF(P14<=4,"Low Risk",IF(P14<=14,"Medium Risk","High Risk")) -> Medium Risk | S14: =IF(R14="High Risk","Treatment",IF(R14="Medium Risk","Treatment","Tolerate")) -> Treatment | T14: Chief Director: Financial Management Services | U14: Awareness campaigns to drivers Communication of circulars and guidelines on utilisation of fleet. | V14: Director: Asset Management | W14: Bi-annual Ongoing
A15: Good Governance | B15: FMS 14 | C15: Financial Management Services | D15: Sub Directorate: Asset Management | E15: Fraud and Corruption | F15: Theft of assets | G15: Deliberate Loss of Assets ie Laptops, Cell phones etc. | H15: Personal gain Non adherence to S45 of the PFMA. Weak Physical security controls. Officials representing the theft of assets whereas they are not stolen. | I15: Financial loss | J15: 3 | K15: 4 | L15: =J15*K15 -> 12 | M15: Asset Verification Asset Management Policy Appointed Loss Control officer (Security Management) | N15: satisfactory | O15: =IF(N15="very good", 0.2, IF(N15="good", 0.4, IF(N15="Satisfactory", 0.6, IF(N15="weak", 0.8, IF(N15="non existent", 1))))) -> 0.6 | P15: =L15*O15 -> 7.2 | Q15: =IF(P15<=4,"Acceptable ",IF(P15<=14,"Moderalety Acceptable","Unacceptable")) -> Moderalety Acceptable | R15: =IF(P15<=4,"Low Risk",IF(P15<=14,"Medium Risk","High Risk")) -> Medium Risk | S15: =IF(R15="High Risk","Treatment",IF(R15="Medium Risk","Treatment","Tolerate")) -> Treatment | T15: Chief Director: Financial Management Services | U15: Awareness on safeguarding of assets. Investigations on lost assets Review of the Asset Management Policy | V15: Director: Asset Management | W15: Ongoing Ongoing Second Quarter
A16: Good Governance | B16: FMS 15 | C16: Financial Management Services | D16: Sub-Directorate : Contract Management | E16: Fraud and Corruption | F16: Contract irregularities | G16: Mismanagement of contracts on implementation i.e. Variation of contract not in writing. | H16: Non-adherence to policies and procedures Lack of enforcement of disciplinary action for non-compliance Inadequate contract extension procedures and or guidelines Lack of management oversight and monitoring of contracts | I16: Financial loss | J16: 3 | K16: 4 | L16: =J16*K16 -> 12 | M16: Contract Checklist and documents received at SCM only | N16: satisfactory | O16: =IF(N16="very good", 0.2, IF(N16="good", 0.4, IF(N16="Satisfactory", 0.6, IF(N16="weak", 0.8, IF(N16="non existent", 1))))) -> 0.6 | P16: =L16*O16 -> 7.2 | Q16: =IF(P16<=4,"Acceptable ",IF(P16<=14,"Moderalety Acceptable","Unacceptable")) -> Moderalety Acceptable | R16: =IF(P16<=4,"Low Risk",IF(P16<=14,"Medium Risk","High Risk")) -> Medium Risk | S16: =IF(R16="High Risk","Treatment",IF(R16="Medium Risk","Treatment","Tolerate")) -> Treatment | T16: Chief Director: Financial Management Services | U16: Verifying bid register with incoming register at Contract Management | V16: Director: Contract Management | W16: Quarterly
A17: Empowered and integrated sustainable communities | B17: DCPM 16 | C17: District Coordination and Project Management | D17: Project Management Unit | E17: Fraud and Corruption | F17: Fraudulent Certification of work | G17: Certification of substandard work on projects | H17: Collusion with stakeholders relevant (businesses) Financial gains No working tools Shortage of human resource Pressure to deliver on targets Pressure to spend the budget. | I17: Financial loss through a need for rectification | J17: 4 | K17: 5 | L17: =J17*K17 -> 20 | M17: National Home Builders Registration Council (NHBRC) South African National Building Regulations (SANBR) Norms and Standards Engineers certificate Inspectors report Re-assign responsibilities among the PMU team | N17: Satisfactory | O17: =IF(N17="very good", 0.2, IF(N17="good", 0.4, IF(N17="Satisfactory", 0.6, IF(N17="weak", 0.8, IF(N17="non existent", 1))))) -> 0.6 | P17: =L17*O17 -> 12 | Q17: =IF(P17<=4,"Acceptable ",IF(P17<=14,"Moderalety Acceptable","Unacceptable")) -> Moderalety Acceptable | R17: =IF(P17<=4,"Low Risk",IF(P17<=14,"Medium Risk","High Risk")) -> Medium Risk | S17: =IF(R17="High Risk","Treatment",IF(R17="Medium Risk","Treatment","Tolerate")) -> Treatment | T17: Chief Director District Coordination and Project Management | U17: Resubmit the request for working tools | V17: Director Project Management Unit (PMU) | W17: Quarter 1
A18: Empowered and integrated sustainable communities | B18: DCPM 17 | C18: District Coordination and Project Management | D18: Grant Management | E18: Fraud and Corruption | F18: Bribery / Kickbacks | G18: Employees accepting bribes from contractors for fictitiious variation oders and to fast track payment of claims. | H18: Unethical behaviour Lifestyle limitations (e.g. highly indebted, substance addiction etc) Non-compliance to policies and procedures | I18: Reputational damage Financial loss | J18: 3 | K18: 4 | L18: =J18*K18 -> 12 | M18: Grant Procedure manual Top Management Intervention / Committee when there is limited funding Anti-Fraud and Corruption Strategy | N18: good | O18: =IF(N18="very good", 0.2, IF(N18="good", 0.4, IF(N18="Satisfactory", 0.6, IF(N18="weak", 0.8, IF(N18="non existent", 1))))) -> 0.4 | P18: =L18*O18 -> 4.8 | Q18: =IF(P18<=4,"Acceptable ",IF(P18<=14,"Moderalety Acceptable","Unacceptable")) -> Moderalety Acceptable | R18: =IF(P18<=4,"Low Risk",IF(P18<=14,"Medium Risk","High Risk")) -> Medium Risk | S18: =IF(R18="High Risk","Treatment",IF(R18="Medium Risk","Treatment","Tolerate")) -> Treatment | T18: Chief Director: District Coordination and Project Management (PMQA) | U18: To ensure that all officials within the section are available for the training Conduct awareness campaigns | V18: Director: Grant Management Director: Risk, Anti-Corruption & Integrity Management Unit | W18: Quarter 1 Quarter 1
A19: Empowered and integrated sustainable communities | B19: DCPM 18 | C19: District Coordination and Project Management | D19: District Coordination | E19: Fraud and Corruption | F19: Poor quality of material | G19: Use of ubstandard material Certification of poor quality material | H19: Scarcity of material Maximising of profits Lack of testing equipment Insufficient funds Demand by communities to use local material | I19: Social unrest (complaints from beneficiaries) Financial loss Poor quality products Litigation against the department | J19: 4 | K19: 4 | L19: 16 | M19: Housing code Project specification and standards South African National Standards NHBRC Inspection Manual | N19: Very good | O19: 0.2 | P19: 3.2 | Q19: Acceptable | R19: Low Risk | S19: Tolerate | T19: Chief Director: District Coordination and Project Management (PMQA) | U19: Undertake a process to procure testing equipment. | V19: Regional Director | W19: Ongoing
A20: Empowered and integrated sustainable communities | B20: DCPM 19 | C20: District Coordination and Project Management | D20: District Coordination | E20: Fraud and Corruption | F20: Misrepresentation of variation orders | G20: Crafting and certification of fictitious variation orders/difficult terrains | H20: Lack of adequate site verification Lack of proper evaluation in the tender processes. Centralisation of tender evaluation processes | I20: Irregular expenditure Blocked projects Negative audit outcome | J20: 5 | K20: 3 | L20: 15 | M20: Housing code Contract terms of reference Site briefing Geotech investigations | N20: Very good | O20: 0.2 | P20: 3 | Q20: Acceptable | R20: Low Risk | S20: Tolerate | T20: Chief Director: District Coordination and Project Management (PMQA) | U20: Propose Incoporation- of affected regional representation in tender evaluation processes | V20: Regional Director | W20: Ongoing
A21: Empowered and integrated sustainable communities | B21: DCPM 20 | C21: District Coordination and Project Management | D21: District Coordination | E21: Fraud and Corruption | F21: Manipulation of units on site | G21: Constructing units of own choice and in wrong sites | H21: Collution with Councillors and Community Liason Officer(s) Nepotism Delays in project implementation | I21: Social unrest Negative audit outcome Blocked projects Irregular expenditure Departmental Impact non responsive to the poorest and the poor. | J21: 5 | K21: 5 | L21: 25 | M21: Beneficiary Assessment (door to door verification of lists) Approved and endorsed beneficiary list from Municipality Linking coordinates with approved beneficiaries Housing Code Housing Subsidy System (HSS) | N21: Good | O21: 0.4 | P21: 10 | Q21: Moderalety Acceptable | R21: Medium Risk | S21: Treatment | T21: Chief Director: District Coordination and Project Management (PMQA) | U21: Effect trainings on ethics Effect ongoing social facilitation | V21: Regional Director | W21: Ongoing
A22: Empowered and integrated sustainable communities | B22: DCPM 21 | C22: District Coordination and Project Management | D22: District Coordination | E22: Fraud and Corruption | F22: Misrepresntation Milestone achievement misrepresentation | G22: Certification of fictitious milestones achievements | H22: Overloaded work Difficult terrains Non replacements of lapsed contract Pressure to reach planned targets (Unlawful instruction from politicians, pressure to utilise budget). Lack/shortage of resources or understaffing (Certifying claims without visit site) Delays in approval of projects | I22: Negative audit outcome Criminal charges Recovering funds from implicated officials Social unrest | J22: 5 | K22: 1 | L22: 5 | M22: Site verification Resident engineer Engineering certificate Housing code Inspectors certificate Housing Subsidy System (HSS) Coordinates linking with beneficiaries | N22: Very good | O22: 0.2 | P22: 1 | Q22: Acceptable | R22: Low Risk | S22: Tolerate | T22: Chief Director: District Coordination and Project Management (PMQA) | U22: Motivate for additional capacity (ratio of inspectors to improve to 1.5) ervan completion report monthly reconcilations Appropriate resources (Request replacements of 4x2 & sedans by 4x4 double cabs) | V22: Regional Directors | W22: Ongoing
A23: Empowered Integrated sustainable communities | B23: HSIP 22 | C23: Human Settlements Incremental Programmes | D23: Special Projects & Remedial Works | E23: Fraud and Corruption | F23: Corruption/Collusion | G23: Collusion between project managers and subcontractors Officials may have opportunity to fast-track other invoices against others for kickbacks (rationalise the act) Substitute materials while billing for higher quality or falsification of pay applications | H23: Kickbacks schemes, Bid rigging at the subcontractor level, Conflict of interest Bribery Lack of close monitoring payment system Third parties manipulate officials Billing for uncompleted work | I23: Image of Department is compromised/Dented (Labelling) Poor control systems | J23: 4 | K23: 4 | L23: 16 | M23: Service Delivery Meetings Reporting Monitoring Conduct regular (sometimes unannounced site visits | N23: Weak | O23: =IF(N23="very good", 0.2, IF(N23="good", 0.4, IF(N23="Satisfactory", 0.6, IF(N23="weak", 0.8, IF(N23="non existent", 1))))) -> 0.8 | P23: 16 | Q23: Unacceptable | R23: High Risk | S23: =IF(R23="High Risk","Treatment",IF(R23="Medium Risk","Treatment","Tolerate")) -> Treatment | T23: Chief Director: Human Settlements Incremental Programmes | U23: Department to embark on intensive fraud awareness programme (visibility to conscientise officials of the wrongs and consequences thereafter Set up a system to receive Anonymous Tips | V23: Fraud and Corruption Directorate | W23: Ongoing
A24: Empowered Integrated sustainable communities | B24: HSIP 23 | C24: Human Settlements Incremental Programmes | D24: Destitute & Vulnerable groups & SPU | E24: Fraud and Corruption | F24: Presentation of inaccurate lists of destitute individuals/families | G24: Misrepresentation of destitute lists submitted for departmental intervention Manipulation of lists for destitute beneficiation | H24: Abuse of power by officials, politicians, traditional leaders who are vested with power in communities | I24: Social unrest Limitation of government impact in dealing with homelessness. Benefitting of non qualifying individuals as destitutse Quee Jumping | J24: 4 | K24: 4 | L24: =J24*K24 -> 16 | M24: Conduct physical verification (means test). Housing code Consolidated lists endorsed by Municipal councils. | N24: Satisfactory | O24: =IF(N24="very good", 0.2, IF(N24="good", 0.4, IF(N24="Satisfactory", 0.6, IF(N24="weak", 0.8, IF(N24="non existent", 1))))) -> 0.6 | P24: =L24*O24 -> 9.6 | Q24: =IF(P24<=4,"Acceptable ",IF(P24<=14,"Moderalety Acceptable","Unacceptable")) -> Moderalety Acceptable | R24: =IF(P24<=4,"Low Risk",IF(P24<=14,"Medium Risk","High Risk")) -> Medium Risk | S24: =IF(R24="High Risk","Treatment",IF(R24="Medium Risk","Treatment","Tolerate")) -> Treatment | T24: Chief Director: Human Settlements Incremental Programmes | U24: Conclude the Policy on Destitute housing and vulnerable groups Consolidate partnerships with municipalities and other relevant stakeholders i.e. SAMVA, NGOs, Masimanyane etc. | V24: Director: Destitute and Vulnerable groups | W24: Third quarter
A25: Empowered Integrated sustainable communities | B25: HSIP 24 | C25: Human Settlements Incremental Programmes | D25: EPHP | E25: Fraud and Corruption | F25: Manipulation of Beneficiary Committees/Community Based Organisation (CBO) | G25: Potential manipulation of beneficiary committee(s) in the recommendation of the Community Resource Organisation (CRO) | H25: Financial gain | I25: Blocked projects Objectives of the policy might not be realised Social unrest Reputational damage Financial loss Possible litigation from other suppliers resulting from such irregular procurement practices Appointment of suppliers who do not have the capacity/financial resources to service GPAA | J25: 5 | K25: 5 | L25: =J25*K25 -> 25 | M25: National Guidelines on EPHP Housing Code | N25: Weak | O25: =IF(N25="very good", 0.2, IF(N25="good", 0.4, IF(N25="Satisfactory", 0.6, IF(N25="weak", 0.8, IF(N25="non existent", 1))))) -> 0.8 | P25: =L25*O25 -> 20 | Q25: =IF(P25<=4,"Acceptable ",IF(P25<=14,"Moderalety Acceptable","Unacceptable")) -> Unacceptable | R25: =IF(P25<=4,"Low Risk",IF(P25<=14,"Medium Risk","High Risk")) -> High Risk | S25: =IF(R25="High Risk","Treatment",IF(R25="Medium Risk","Treatment","Tolerate")) -> Treatment | T25: Chief Director: Human Settlements Incremental Programmes | U25: Finalising Provincial guidelines on EPHP Alignment of the procurement process with PPPFA (Be specific on the PPPFA provisions in question) | V25: Director: EmErgency housing and EPHP | W25: Fourth quarter
A26: Empowered Integrated sustainable communities | B26: HSIP 25 | C26: Human Settlements Incremental Programmes | D26: Emergency Housing | E26: Fraud and Corruption | F26: Misrepresentation of Beneficiary List , claims, Shelters | G26: submission of fictitious Claims submitted by service provider to deliberate deception the Department . i.e duplicate claims , non existences , claims for the working that is done or uncompleted work Manipulation of beneficiary Lists for shelters .i.e Beneficairy that are not in need of temparary shelters reflecting on the request list Collusion between officials and service provider to submit fraudulent claims i.e .inflated prices | H26: Financial gain Weakness of Control Unethical Behaviour automated systems Poor Quality control to check material standard False submisson of structure typology by Service Provider A political will to for realisation of development (Councillors recognition) Lacking understanding of emergency cases Opportunity from official/s that adds their own people | I26: Fruitless and wasteful expenditure No value created Financial Losses Reputational damage to government/ Department Litgation cases | J26: 5 | K26: 4 | L26: =J26*K26 -> 20 | M26: Emergency Housing Policy Emergency Grant Framework Physical verification to affected beneficiary Emergency Housing Policy Emergency Grant Framework | N26: Weak | O26: =IF(N26="very good", 0.2, IF(N26="good", 0.4, IF(N26="Satisfactory", 0.6, IF(N26="weak", 0.8, IF(N26="non existent", 1))))) -> 0.8 | P26: =L26*O26 -> 16 | Q26: =IF(P26<=4,"Acceptable ",IF(P26<=14,"Moderalety Acceptable","Unacceptable")) -> Unacceptable | R26: =IF(P26<=4,"Low Risk",IF(P26<=14,"Medium Risk","High Risk")) -> High Risk | S26: =IF(R26="High Risk","Treatment",IF(R26="Medium Risk","Treatment","Tolerate")) -> Treatment | T26: Chief Director: Human Settlements Incremental Programmes | U26: Submit a request Nationa Office Human Settlemets Department rights to utlise HSS for loadin gof beneficiary ( for temporary shelts) . To provide intense training to the Control Works Inspectors to undestand the TRUs specification and requirement on erection of TRUs. To upadate and document our process flow by only approving structures that are signed by Proffession Engenerings . Colaboration with Muncipal officials to intensify and streghten the process of verification of emergency beneifiary list | V26: Director: EmErgency housing and EPHP | W26: Fourth quarter
A27: Empowered Integrated sustainable communities | B27: HSIP 26 | C27: Human Settlements Incremental Programmes | D27: Informal Settlements Upgrading | E27: Fraud and Corruption | F27: Misrepresentaton of the list of informal settlements and information by Service Providers | G27: Unsubstantiated list of informal settlements to be upgraded to submitted by the municipalities Dishonourable ( Misleading )and fraudulent project invoices and claims on value created Certification of substandard work on projects | H27: Reprioritisation of the selected informal settlement by municipality without consideration of approved informal settlements Councillors/committee members seeking financial and political gains misinformation and misunderstanding of the program objectives Non-compliance to policies and procedures in the value chain Lack of Monitoring and control Collusion with relevant stakeholders | I27: Fiscal constraints on Budget for the upgrading of the informal settlements(grant) Social unrest and community disturbilisation Delays in beneficiation of rightful households in the upgrading projects Blocked upgrading projects Fruitless and wasteful expenditure leading to financial loss (Fraud and Corruption) Inability to complete projects Project outcome inconsistent with objectives | J27: 3 | K27: 3 | L27: =J27*K27 -> 9 | M27: Integrated Development Plan (IDP) Municipal Council Resolutions Housing Code Systems Description and process flows Informal Settlements Upgrading Partnership Grant (ISUPG) framework (DORA) Provincial Supply chain policy | N27: Satisfactory | O27: =IF(N27="very good", 0.2, IF(N27="good", 0.4, IF(N27="Satisfactory", 0.6, IF(N27="weak", 0.8, IF(N27="non existent", 1))))) -> 0.6 | P27: =L27*O27 -> 5.4 | Q27: =IF(P27<=4,"Acceptable ",IF(P27<=14,"Moderalety Acceptable","Unacceptable")) -> Moderalety Acceptable | R27: =IF(P27<=4,"Low Risk",IF(P27<=14,"Medium Risk","High Risk")) -> Medium Risk | S27: =IF(R27="High Risk","Treatment",IF(R27="Medium Risk","Treatment","Tolerate")) -> Treatment | T27: Chief Director: Human Settlements Incremental Programmes | U27: Education and orientation ( Training )of the programme to the municipalities and communities Continuous verification of the informal settlements to be upgraded Strengthening of the project terms of reference using supply chain guidelines Strengthening of non compliance from the supply chain policies | V27: Director: ISUP | W27: Quartely Quarterly
J28: 3 | K28: 3 | L28: =J28*K28 -> 9 | N28: Satisfactory | O28: =IF(N28="very good", 0.2, IF(N28="good", 0.4, IF(N28="Satisfactory", 0.6, IF(N28="weak", 0.8, IF(N28="non existent", 1))))) -> 0.6 | P28: =L28*O28 -> 5.4 | Q28: =IF(P28<=4,"Acceptable ",IF(P28<=14,"Moderalety Acceptable","Unacceptable")) -> Moderalety Acceptable | R28: =IF(P28<=4,"Low Risk",IF(P28<=14,"Medium Risk","High Risk")) -> Medium Risk | S28: =IF(R28="High Risk","Treatment",IF(R28="Medium Risk","Treatment","Tolerate")) -> Treatment
J29: 3 | K29: 3 | L29: =J29*K29 -> 9 | N29: Satisfactory | O29: =IF(N29="very good", 0.2, IF(N29="good", 0.4, IF(N29="Satisfactory", 0.6, IF(N29="weak", 0.8, IF(N29="non existent", 1))))) -> 0.6 | P29: =L29*O29 -> 5.4 | Q29: =IF(P29<=4,"Acceptable ",IF(P29<=14,"Moderalety Acceptable","Unacceptable")) -> Moderalety Acceptable | R29: =IF(P29<=4,"Low Risk",IF(P29<=14,"Medium Risk","High Risk")) -> Medium Risk | S29: =IF(R29="High Risk","Treatment",IF(R29="Medium Risk","Treatment","Tolerate")) -> Treatment
J30: 3 | K30: 3 | L30: =J30*K30 -> 9 | N30: Satisfactory | O30: =IF(N30="very good", 0.2, IF(N30="good", 0.4, IF(N30="Satisfactory", 0.6, IF(N30="weak", 0.8, IF(N30="non existent", 1))))) -> 0.6 | P30: =L30*O30 -> 5.4 | Q30: =IF(P30<=4,"Acceptable ",IF(P30<=14,"Moderalety Acceptable","Unacceptable")) -> Moderalety Acceptable | R30: =IF(P30<=4,"Low Risk",IF(P30<=14,"Medium Risk","High Risk")) -> Medium Risk | S30: =IF(R30="High Risk","Treatment",IF(R30="Medium Risk","Treatment","Tolerate")) -> Treatment
J31: 3 | K31: 3 | L31: =J31*K31 -> 9 | N31: Satisfactory | O31: =IF(N31="very good", 0.2, IF(N31="good", 0.4, IF(N31="Satisfactory", 0.6, IF(N31="weak", 0.8, IF(N31="non existent", 1))))) -> 0.6 | P31: =L31*O31 -> 5.4 | Q31: =IF(P31<=4,"Acceptable ",IF(P31<=14,"Moderalety Acceptable","Unacceptable")) -> Moderalety Acceptable | R31: =IF(P31<=4,"Low Risk",IF(P31<=14,"Medium Risk","High Risk")) -> Medium Risk | S31: =IF(R31="High Risk","Treatment",IF(R31="Medium Risk","Treatment","Tolerate")) -> Treatment
J32: 3 | K32: 3 | L32: =J32*K32 -> 9 | N32: Satisfactory | O32: =IF(N32="very good", 0.2, IF(N32="good", 0.4, IF(N32="Satisfactory", 0.6, IF(N32="weak", 0.8, IF(N32="non existent", 1))))) -> 0.6 | P32: =L32*O32 -> 5.4 | Q32: =IF(P32<=4,"Acceptable ",IF(P32<=14,"Moderalety Acceptable","Unacceptable")) -> Moderalety Acceptable | R32: =IF(P32<=4,"Low Risk",IF(P32<=14,"Medium Risk","High Risk")) -> Medium Risk | S32: =IF(R32="High Risk","Treatment",IF(R32="Medium Risk","Treatment","Tolerate")) -> Treatment
J33: 3 | K33: 3 | L33: =J33*K33 -> 9 | N33: Satisfactory | O33: =IF(N33="very good", 0.2, IF(N33="good", 0.4, IF(N33="Satisfactory", 0.6, IF(N33="weak", 0.8, IF(N33="non existent", 1))))) -> 0.6 | P33: =L33*O33 -> 5.4 | Q33: =IF(P33<=4,"Acceptable ",IF(P33<=14,"Moderalety Acceptable","Unacceptable")) -> Moderalety Acceptable | R33: =IF(P33<=4,"Low Risk",IF(P33<=14,"Medium Risk","High Risk")) -> Medium Risk | S33: =IF(R33="High Risk","Treatment",IF(R33="Medium Risk","Treatment","Tolerate")) -> Treatment
J34: 3 | K34: 3 | L34: =J34*K34 -> 9 | N34: Satisfactory | O34: =IF(N34="very good", 0.2, IF(N34="good", 0.4, IF(N34="Satisfactory", 0.6, IF(N34="weak", 0.8, IF(N34="non existent", 1))))) -> 0.6 | P34: =L34*O34 -> 5.4 | Q34: =IF(P34<=4,"Acceptable ",IF(P34<=14,"Moderalety Acceptable","Unacceptable")) -> Moderalety Acceptable | R34: =IF(P34<=4,"Low Risk",IF(P34<=14,"Medium Risk","High Risk")) -> Medium Risk | S34: =IF(R34="High Risk","Treatment",IF(R34="Medium Risk","Treatment","Tolerate")) -> Treatment
J35: 3 | K35: 3 | L35: =J35*K35 -> 9 | N35: Satisfactory | O35: =IF(N35="very good", 0.2, IF(N35="good", 0.4, IF(N35="Satisfactory", 0.6, IF(N35="weak", 0.8, IF(N35="non existent", 1))))) -> 0.6 | P35: =L35*O35 -> 5.4 | Q35: =IF(P35<=4,"Acceptable ",IF(P35<=14,"Moderalety Acceptable","Unacceptable")) -> Moderalety Acceptable | R35: =IF(P35<=4,"Low Risk",IF(P35<=14,"Medium Risk","High Risk")) -> Medium Risk | S35: =IF(R35="High Risk","Treatment",IF(R35="Medium Risk","Treatment","Tolerate")) -> Treatment
J36: 3 | K36: 3 | L36: =J36*K36 -> 9 | N36: Satisfactory | O36: =IF(N36="very good", 0.2, IF(N36="good", 0.4, IF(N36="Satisfactory", 0.6, IF(N36="weak", 0.8, IF(N36="non existent", 1))))) -> 0.6 | P36: =L36*O36 -> 5.4 | Q36: =IF(P36<=4,"Acceptable ",IF(P36<=14,"Moderalety Acceptable","Unacceptable")) -> Moderalety Acceptable | R36: =IF(P36<=4,"Low Risk",IF(P36<=14,"Medium Risk","High Risk")) -> Medium Risk | S36: =IF(R36="High Risk","Treatment",IF(R36="Medium Risk","Treatment","Tolerate")) -> Treatment
J37: 3 | K37: 3 | L37: =J37*K37 -> 9 | N37: Satisfactory | O37: =IF(N37="very good", 0.2, IF(N37="good", 0.4, IF(N37="Satisfactory", 0.6, IF(N37="weak", 0.8, IF(N37="non existent", 1))))) -> 0.6 | P37: =L37*O37 -> 5.4 | Q37: =IF(P37<=4,"Acceptable ",IF(P37<=14,"Moderalety Acceptable","Unacceptable")) -> Moderalety Acceptable | R37: =IF(P37<=4,"Low Risk",IF(P37<=14,"Medium Risk","High Risk")) -> Medium Risk | S37: =IF(R37="High Risk","Treatment",IF(R37="Medium Risk","Treatment","Tolerate")) -> Treatment
J38: 3 | K38: 3 | L38: =J38*K38 -> 9 | N38: Satisfactory | O38: =IF(N38="very good", 0.2, IF(N38="good", 0.4, IF(N38="Satisfactory", 0.6, IF(N38="weak", 0.8, IF(N38="non existent", 1))))) -> 0.6 | P38: =L38*O38 -> 5.4 | Q38: =IF(P38<=4,"Acceptable ",IF(P38<=14,"Moderalety Acceptable","Unacceptable")) -> Moderalety Acceptable | R38: =IF(P38<=4,"Low Risk",IF(P38<=14,"Medium Risk","High Risk")) -> Medium Risk | S38: =IF(R38="High Risk","Treatment",IF(R38="Medium Risk","Treatment","Tolerate")) -> Treatment
J39: 3 | K39: 3 | L39: =J39*K39 -> 9 | N39: Satisfactory | O39: =IF(N39="very good", 0.2, IF(N39="good", 0.4, IF(N39="Satisfactory", 0.6, IF(N39="weak", 0.8, IF(N39="non existent", 1))))) -> 0.6 | P39: =L39*O39 -> 5.4 | Q39: =IF(P39<=4,"Acceptable ",IF(P39<=14,"Moderalety Acceptable","Unacceptable")) -> Moderalety Acceptable | R39: =IF(P39<=4,"Low Risk",IF(P39<=14,"Medium Risk","High Risk")) -> Medium Risk | S39: =IF(R39="High Risk","Treatment",IF(R39="Medium Risk","Treatment","Tolerate")) -> Treatment
... J83: 3 | K83: 3 | L83: =J83*K83 -> 9 | N83: Satisfactory | O83: =IF(N83="very good", 0.2, IF(N83="good", 0.4, IF(N83="Satisfactory", 0.6, IF(N83="weak", 0.8, IF(N83="non existent", 1))))) -> 0.6 | P83: =L83*O83 -> 5.4 | Q83: =IF(P83<=4,"Acceptable ",IF(P83<=14,"Moderalety Acceptable","Unacceptable")) -> Moderalety Acceptable | R83: =IF(P83<=4,"Low Risk",IF(P83<=14,"Medium Risk","High Risk")) -> Medium Risk | S83: =IF(R83="High Risk","Treatment",IF(R83="Medium Risk","Treatment","Tolerate")) -> Treatment

Sheet Emerging Risk Register 
B5: EMERGING RISK REGISTER 2025/26
A9: Link to Outcome | B9: Risk number | C9: Unit | D9: Risk Category | E9: Risk Description | F9: Risk Causes | G9: Consequences | H9: Impact Value (1-5) | I9: Likelihood Value (1-5) | J9: Inherent Risk Value | K9: Current controls | L9: Control Effectiveness | M9: Effectiveness rating | N9: Residual Risk Value | O9: Risk Appetite | P9: Risk Tolerance | Q9: Suggested Risk Response | R9: Risk Owner | S9: Action to improve management of the risk | T9: Action owner | U9: Timeline
A10: Socially cohesive and economically viable communities with access to basic services, housing, and economic opportunities | B10: ER-1 | D10: Service delivery | E10: Increased public service protests | F10: Upcoming Local Government Elections | G10: Service delivery disruptions Delays in the implementation of projects Reputational Damage Safety concerns of empoyees | H10: 5 | I10: 5 | J10: =H10*I10 -> 25 | K10: Implementation of departmental social facilitation strategy Hands on support provided to municipalities | L10: satisfactory | M10: =IF(L10="very good", 0.2, IF(L10="good", 0.4, IF(L10="Satisfactory", 0.6, IF(L10="weak", 0.8, IF(L10="non existent", 1))))) -> 0.6 | N10: =J10*M10 -> 15 | O10: =IF(N10<=4,"Acceptable ",IF(N10<=14,"Moderalety Acceptable","Unacceptable")) -> Unacceptable | P10: =IF(N10<=4,"Low Risk",IF(N10<=14,"Medium Risk","High Risk")) -> High Risk | Q10: =IF(P10="High Risk","Treatment",IF(P10="Medium Risk","Treatment","Tolerate")) -> Treatment | R10: Chief Directors | S10: All Directorates and HandsOn support personnel that renders social facilitation functions will be capacitated on social facilitation strategy in order to curb service delivery protests during the election period
A11: Socially cohesive and economically viable communities with access to basic services, housing, and economic opportunities | B11: ER-2 | C11: Human Settlements Incremental Programme | D11: Service delivery | E11: Reduction of ISUPG budget to complete the Phase 3 upgrading | G11: The projects completion will be delayed to the outer years Budget cuts may result in unfinished or substandard infrastructure, affecting long-term sustainability and the formalization of tenure (e.g., issuing title deeds). These delays will undermine legal security for residents and discourage investment in home improvements leading to loss of Community Trust, and feeling of betrayed The Risk of revert to informal conditions, of having services that are unreliable or unsafe. South Africa’s commitments under the Sustainable Development Goals (SDGs) and National Development Plan (NDP) may be compromised due to underperformance in informal settlement upgrading. | H11: 5 | I11: 5 | J11: =H11*I11 -> 25 | L11: very good | M11: =IF(L11="very good", 0.2, IF(L11="good", 0.4, IF(L11="Satisfactory", 0.6, IF(L11="weak", 0.8, IF(L11="non existent", 1))))) -> 0.2 | N11: =J11*M11 -> 5 | O11: =IF(N11<=4,"Acceptable ",IF(N11<=14,"Moderalety Acceptable","Unacceptable")) -> Moderalety Acceptable | P11: =IF(N11<=4,"Low Risk",IF(N11<=14,"Medium Risk","High Risk")) -> Medium Risk | Q11: =IF(P11="High Risk","Treatment",IF(P11="Medium Risk","Treatment","Tolerate")) -> Treatment | R11: Chief Director:
A12: Socially cohesive and economically viable communities with access to basic services, housing, and economic opportunities | B12: ER-3 | C12: Human Settlements Incremental Programme | D12: Service delivery | E12: The demand for emergency housing assistance has increased thus straining the budget allocation for the province | F12: Lack of response to disasters by the National Department | G12: Families left without shelter | H12: 5 | I12: 5 | J12: =H12*I12 -> 25 | L12: good | M12: =IF(L12="very good", 0.2, IF(L12="good", 0.4, IF(L12="Satisfactory", 0.6, IF(L12="weak", 0.8, IF(L12="non existent", 1))))) -> 0.4 | N12: =J12*M12 -> 10 | O12: =IF(N12<=4,"Acceptable ",IF(N12<=14,"Moderalety Acceptable","Unacceptable")) -> Moderalety Acceptable | P12: =IF(N12<=4,"Low Risk",IF(N12<=14,"Medium Risk","High Risk")) -> Medium Risk | Q12: =IF(P12="High Risk","Treatment",IF(P12="Medium Risk","Treatment","Tolerate")) -> Treatment | R12: Director:
A13: Socially cohesive and economically viable communities with access to basic services, housing, and economic opportunities | B13: ER-4 | C13: District Coordination and Project Management | D13: Financial | E13: Failure to remove asbestos. | F13: Unfunded madate | G13: Legal exposure if the issue is not addressed properly. | H13: 5 | I13: 5 | J13: =H13*I13 -> 25 | L13: satisfactory | M13: =IF(L13="very good", 0.2, IF(L13="good", 0.4, IF(L13="Satisfactory", 0.6, IF(L13="weak", 0.8, IF(L13="non existent", 1))))) -> 0.6 | N13: =J13*M13 -> 15 | O13: =IF(N13<=4,"Acceptable ",IF(N13<=14,"Moderalety Acceptable","Unacceptable")) -> Unacceptable | P13: =IF(N13<=4,"Low Risk",IF(N13<=14,"Medium Risk","High Risk")) -> High Risk | Q13: =IF(P13="High Risk","Treatment",IF(P13="Medium Risk","Treatment","Tolerate")) -> Treatment | R13: Chief Director: | S13: Request for funding to National for Data collection of houses with Asbestos roofs and ceiling .
A14: Enhanced governance for service delivery efficiency | B14: ER-5 | C14: Corporate Services | D14: Compliance / Regulatory | E14: Non-Allocation and Non-Utilization of microsoft licenses | F14: Reporting (Microsoft BI) tool not showing correct statistics. High vacancy rate (16%) / Unavoidable delays in the filling of vacant posts. Recurring levels of staff movement (resignations, retirements, deaths, Policy and Procedure on Incapacity Leave and Ill-Health Retirement (PILIR) cases) Inactive/Offline users. Hybrid (Physical vs Virtual Meetings vs Remote/off-Site) working environment / decline on the use of Microsoft Virtual meetings User resistance / Use of private / alternative tools for collaboration, sharing and communicating such as WhatsApp, Zoom, Google meet, Gmails. Incorrect Metrics for calculation of Microsoft utilization (Active users / Enabled Users including guest users). Poor planning, adoption, allocation and usage of Microsoft applications. Poor password management (end-user). | G14: Fruitless and wasteful expenditure Negative audit outcomes Delays in digital transformation | H14: 4 | I14: 5 | J14: =H14*I14 -> 20 | K14: User access quarterly reviews Training and User awareness sessions Enforced password policy. Annual Demand plan (CPS). Operational Levell Agreement (OLA) between OTP and ECDHS (The Parties agree that a threshold of 90% (with a tolerance level of 10%)) . Logged a call with Microsoft for Reconfiguration the of BI Reporting tool using correct data metrix (Active users / Ourchased Licences). | L14: satisfactory | M14: =IF(L14="very good", 0.2, IF(L14="good", 0.4, IF(L14="Satisfactory", 0.6, IF(L14="weak", 0.8, IF(L14="non existent", 1))))) -> 0.6 | N14: =J14*M14 -> 12 | O14: =IF(N14<=4,"Acceptable ",IF(N14<=14,"Moderalety Acceptable","Unacceptable")) -> Moderalety Acceptable | P14: =IF(N14<=4,"Low Risk",IF(N14<=14,"Medium Risk","High Risk")) -> Medium Risk | Q14: =IF(P14="High Risk","Treatment",IF(P14="Medium Risk","Treatment","Tolerate")) -> Treatment | R14: Chief Director: Corporate services | S14: Define ECDHS Microsoft utilisation report with correct Data Metrix (Active users / Purchased Licenses). Conduct Training and Awareness sessions( on use of Ms Teams and Sharepoint online) Continues monitoring of Microsoft utilisation and allocation through Microsoft BI Reporting tool. Reconfigure policies to enforce password sync for microsoft apps Consult/engage inactive users and provide hands-on support. Teams: Promote utilization of Virtual meetings more habitually, instead of Physical meetings. E365: Conduct Data Cleansing (Systems reviews) quarterly Share Point: - Optimise use of SharePoint Storage. Implement IT plan (Digitisation and Automation) initiatives. OneDrive: Migrate remaining users to OneDrive and enforce utilization through Group policy. Engage OTP / PGITOC (EC) quarterly meetings, to review the performance of the Microsoft Enterprise Agreements. Filling vacant positions. | T14: Director:ICT | U14: Quartely
H15: 5 | I15: 5 | J15: =H15*I15 -> 25 | L15: weak | M15: =IF(L15="very good", 0.2, IF(L15="good", 0.4, IF(L15="Satisfactory", 0.6, IF(L15="weak", 0.8, IF(L15="non existent", 1))))) -> 0.8 | N15: =J15*M15 -> 20 | O15: =IF(N15<=4,"Acceptable ",IF(N15<=14,"Moderalety Acceptable","Unacceptable")) -> Unacceptable | P15: =IF(N15<=4,"Low Risk",IF(N15<=14,"Medium Risk","High Risk")) -> High Risk | Q15: =IF(P15="High Risk","Treatment",IF(P15="Medium Risk","Treatment","Tolerate")) -> Treatment | R15: Chief Director:
H16: 5 | I16: 5 | J16: =H16*I16 -> 25 | L16: good | M16: =IF(L16="very good", 0.2, IF(L16="good", 0.4, IF(L16="Satisfactory", 0.6, IF(L16="weak", 0.8, IF(L16="non existent", 1))))) -> 0.4 | N16: =J16*M16 -> 10 | O16: =IF(N16<=4,"Acceptable ",IF(N16<=14,"Moderalety Acceptable","Unacceptable")) -> Moderalety Acceptable | P16: =IF(N16<=4,"Low Risk",IF(N16<=14,"Medium Risk","High Risk")) -> Medium Risk | Q16: =IF(P16="High Risk","Treatment",IF(P16="Medium Risk","Treatment","Tolerate")) -> Treatment | R16: Chief Director:
A17: Signature: __________________
A19: Date: __________________

Sheet Risk Rating Tables 
A1: IMPACT (CONSEQUENCE)
A2: Rating | B2: Assessment | C2: Definition
A3: 1 | B3: Insignificant | C3: Negative outcomes or missed opportunities that are likely to have a negligible impact on the ability to meet outcomes
A4: 2 | B4: Minor | C4: Negative outcomes or missed opportunities that are likely to have a relatively low impact on the ability to meet outcomes
A5: 3 | B5: Moderate | C5: Negative outcomes or missed opportunities that are likely to have a relatively moderate impact on the ability to meet outcomes
A6: 4 | B6: Major | C6: Negative outcomes or missed opportunities that are likely to have a relatively substantial impact on the ability to meet outcomes
A7: 5 | B7: Critical | C7: Negative outcomes or missed opportunities that are of critical importance to the achievement of the outcomes
A9: LIKELIHOOD (FREQUENCY, PROBABILITY)
A10: Rating | B10: Assessment | C10: Definition
A11: 1 | B11: Rare | C11: The risk is conceivable but is only likely to occur in extreme circumstances
A12: 2 | B12: Unlikely | C12: The risk occurs infrequently and is unlikely to occur within the next 3 years
A13: 3 | B13: Moderate | C13: There is an above average chance that the risk will occur at least once in the next 3 years
A14: 4 | B14: Likely | C14: The risk could easily occur, and is likely to occur at least once within the next 12 months
A15: 5 | B15: Common | C15: The risk is already occurring, or is likely to occur more than once within the next 12 months

Sheet Risk Categories 
A4: RISK CATEGORIES
B6: Risk category | C6: Description
B7: Human resources | C7: Risks that relate to human resources of an institution. These risks can have an effect on an institution's human capital with regard to:
C8: Integrity and honesty;
C9: Recruitment;
C10: Skills and competence;
C11: Employee wellness;
C12: Employee relations;
C13: Retention; and
C14: Occupational health and safety.
B15: Knowledge and Information management | C15: Risks relating to an institution's management of knowledge and information. In identifying the risks consider the following aspects related to knowledge management:
C16: Availability of information;
C17: Stability of the information;
C18: Integrity of information data;
C19: Relevance of the information;
C20: Retention; and
C21: Safeguarding.
B22: Litigation | C22: Risks that the institution might suffer losses due to litigation and lawsuits against it. Losses from litigation can possibly emanate from:
C24: Claims by employees, the public, service providers and other third party
C25: Failure by an institution to exercise certain rights that are to its advantage
B26: Loss \ theft of assets | C26: Risks that an institution might suffer losses due to either theft or loss of an asset of the institution.
B28: Service delivery | C28: Every institution exists to provide value for its stakeholders. The risk will arise if the appropriate quality of service is not delivered to the citizens.
B29: Information Technology | C29: The risks relating specifically to the institution's IT objectives, infrastructure requirement, etc. Possible considerations could include the following when identifying applicable risks:
C31: Security concerns;
C32: Technology availability (uptime);
C33: Applicability of IT infrastructure;
C34: Integration / interface of the systems;
C35: Effectiveness of technology; and
C36: Obsolescence of technology.
B37: Third party performance | C37: Risks related to an institution's dependence on the performance of a third party. Risk in this regard could be that there is the likelihood that a service provider might not perform according to the service level agreement entered into with an institution. Non performance could include:
C39: Outright failure to perform;
C40: Not rendering the required service in time;
C41: Not rendering the correct service; and
C42: Inadequate / poor quality of performance.
B43: Health & Safety | C43: Risks from occupational health and safety issues e.g. injury on duty; outbreak of disease within the institution.
B44: Disaster recovery / business continuity | C44: Risks related to an institution's preparedness or absence thereto to disasters that could impact the normal functioning of the institution e.g. natural disasters, act of terrorism etc. This would lead to the disruption of processes and service delivery and could include the possible disruption of operations at the onset of a crisis to the resumption of critical activities. Factors to consider include:
C46: Disaster management procedures; and
C47: Contingency planning.
B48: Compliance \ Regulatory | C48: Risks related to the compliance requirements that an institution has to meet. Aspects to consider in this regard are:
C50: Failure to monitor or enforce compliance
C51: Monitoring and enforcement mechanisms;
C52: Consequences of non compliance; and
C53: Fines and penalties paid.
B54: Fraud and corruption | C54: These risks relate to illegal or improper acts by employees resulting in a loss of the institution's assets or resources.
B55: Financial | C55: Risks encompassing the entire scope of general financial management. Potential factors to consider include:
C57: Cash flow adequacy and management thereof;
C58: Financial losses;
C59: Wasteful expenditure;
C60: Budget allocations;
C61: Financial statement integrity;
C62: Revenue collection; and
C63: Increasing operational expenditure.
B64: Cultural | C64: Risks relating to an institution's overall culture and control environment. The various factors related to organisational culture include:
C66: Communication channels and the effectiveness;
C67: Cultural integration;
C68: Entrenchment of ethics and values;
C69: Goal alignment; and
C70: Management style.
B71: Reputation | C71: Factors that could result in the tarnishing of an institution's reputation, public perception and image.
B72: Economic Environment | C72: Risks related to the institution's economic environment. Factors to consider include:
C74: Inflation;
C75: Foreign exchange fluctuations; and
C76: Interest rates.
B77: Political environment | C77: Risks emanating from political factors and decisions that have an impact on the institution's mandate and operations. Possible factors to consider include:
C78: Political unrest;
C79: Local, Provincial and National elections; and
C80: Changes in office bearers.
B81: Natural environment | C81: Risks relating to the institution's natural environment and its impact on normal operations. Consider factors such as:
C82: Depletion of natural resources;
C83: Environmental degradation;
C84: Spillage; and
C85: Pollution.
B86: Technological environment | C86: Risks emanating from the effects of advancements and changes in technology.
B87: Legislative environment | C87: Risks related to the institution's legislative environment e.g. changes in legislation, conflicting legislation.
B88: Material resources(procurement risk) | C88: Risks relating to an Institution's material resources. Possible aspects to consider include: • Availability of material; • Costs and means of acquiring \ procuring resources; and • The wastage of material resources
B89: Social environment | C89: Risks related to the Institution's social environment. Possible factors to consider include: • Unemployment; and • Migration of workers. Risks related to the Institution's social environment. Possible factors to consider include: • Unemployment; and • Migration of workers.

Sheet Tolerance
C1: RISK APPETITE LEVEL | F1: RISK TOLERANCE THRESHOLDS
A2: No | B2: Category | C2: Acceptable | D2: Moderately Acceptable | E2: Unacceptable | F2: Low Risk | G2: Medium Risk | H2: High Risk | J2: Low | K2: Non-existent
C3: 1 to 4 | D3: 5 to 14 | E3: 15 - 25 | F3: 1 to 4 | G3: 5 to 14 | H3: 15 - 25 | J3: Medium | K3: Weak
A4: 1 | B4: Human Resources | C4: Risk has little effect on Objective Accept with Minor Monitoring | D4: Risk does affect Objective Accept with Regular Monitor | E4: Risk Severely Affects Objective Accept with Rigorous/ | F4: Accept/Tolerate | G4: Treat Transfer | H4: Terminate Treat | J4: High | K4: Satisfactory
E5: Continuous Monitoring | K5: Good
K6: Very Good
A8: Within the organisation’s risk capacity it has determined that it must have an appetite for the categories of risk as indicated. The risk appetite is further enhanced to indicate management’s considerations on different levels of inherent risk.
A9: Sequence of risk management actions and application of the Appetite and Tolerance levels:
A10: 1. A risk is identified.
A11: 2. The risk is categorised.
A12: 3. The risk is linked to an objective.
A13: 4. Inherent impact and likelihood is determined and Inherent Risk Score is determined (Impact X Likelihood)
A14: 5. Risk Appetite Level is considered:
A15: a. If the Inherent risk score is between 1 – 4 the risk has little effect on the objective and minor treatment and monitoring should be considered to lower the residual risk;
A16: b. If the Inherent risk score is between 5 – 14 the risk does affect the objective can be accepted but regular monitoring and effective controls will have to be instated to reduce residual risk to tolerable levels;
A17: c. If the Inherent risk score is between 15 – 25 the risk severely affects the objective. If it is unavoidable to accept the risk (e.g. it is imposed by legislation, by mandate etc.), the risk is accepted but will be rigorously controlled and monitored. Strong controls will have to be implemented and regularly tested and continuous monitoring should take place.
A18: 6. Once the risk is accepted and the appetite has been determined the tolerance level should be set. The control effectiveness rating will have an effect on the Inherent Impact and/or Likelihood Scoring.
A19: a. If the control is effective and the risk scoring is reduced to between 1 – 4 then the risk is managed within the Low Risk tolerance level.
... A25: c. Tolerate (for low risk items).
B27: Low | D27: Non-existent | E27: 1
B28: Medium | D28: Weak | E28: 0.8
B29: High | D29: Satisfactory | E29: 0.6 | F29: very good
D30: Good | E30: 0.4 | F30: good
D31: Very Good | E31: 0.2 | F31: satisfactory
F32: weak
F33: non existent
B35: Human Resource
B36: Knowledge and Information Management
B37: Litigation
B38: Loss/ theft of assets
B39: Material resources (procurement risk)
B40: Service delivery
B41: Information Technology
B42: Third party performance
B43: Health & Safety
B44: Disaster recovery/business continuity
B45: Compliance / Regulatory
B46: Fraud & corruption
... B55: Legislative Environment
B58: Yes | C58: Completed
B59: No | C59: Partially Complete
C60: Not Completed
B64: =IF(N10<=4,"Acceptable ",IF(N10<=14,"Moderalety Acceptable","Unacceptable")) -> Acceptable

Sheet Control & RM effectiveness
A1: Effectiveness category | B1: Category definition | C1: Factor
A2: Very good | B2: Risk exposure is effectively controlled and managed | C2: 0.2
A3: Good | B3: Majority of risk exposure is effectively controlled and managed | C3: 0.4
A4: Satisfactory | B4: There is room for some improvement | C4: 0.6
A5: Weak | B5: Some of the risk exposure appears to be controlled, but there are major deficiencies | C5: 0.8
A6: Non existent | B6: Control measures do not exist | C6: 1

Sheet Dashboard 
A1: CHIEF DIRECTORATE | B1: RISK NO. | C1: RISK DESCRIPTION | D1: RESIDUAL AS AT MARCH 2025 | E1: OVERALL PROGRESSS TO DATE ON THE IMPLEMENTATION OF ACTION PLANS TO ADDRESS THE RISK | F1: RESIDUAL AS AT MARCH 2026 | G1: ACTION OWNER | H1: Residual Risk Value as at 30 June 2025
A2: CS | B2: CS-1 | C2: Inadequate management of performance by supervisors | E2: Continuous implementation of EPMDS quality control checklist | F2: Director HRD &OD | G2: Quarterly
A3: CS | B3: CS-2 | C3: Incorrect record of Leave accruals | E3: The Risk has been tolerated in as far as the Risk Tolerance level, however risk is still managed. | F3: Director HRM | G3: Quarterly
A4: CS | B4: CS-3 | C4: Default Judgements | E4: The Risk has been tolerated in as far as the Risk Tolerance level, however risk is still managed. | F4: Director : Legal | G4: Quarterly | H4: ='Register 2025-26'!V12 -> 0
A5: CS | B5: ICT-01 | C5: Inadequate management of Departmental records and knowledge | E5: Conduct awarenesses on records management | F5: Director:GICTM | G5: Quarterly
A6: HSFP | B6: HSFP-1 | C6: Illegal occupation and use of houses | E6: Establishment and monitoring of Beneficiary Allocation Committees to ensure fairness in the allocation process and to avoid possible misallocation and wrongful occupation of houses | F6: Director: Beneficiary Management | G6: Quarterly | H6: ='Register 2025-26'!V14 -> 0
A7: HSFP | B7: HSFP-2 | C7: Inadequate implementation of facilitation interventions | E7: Implementation of the Social Facilitation Strategy | F7: Director: Social Facilitation and Customer Care | G7: Quarterly | H7: ='Register 2025-26'!V15 -> 0
A8: HSFP | B8: HSFP-3 | C8: Procurement of 40% MSMEs from the framework agreement may not be achieved. | E8: Acquire lists of MSME contractors appointed by the region who are utilizing 40% of the Human Settlements’ Conditional Grant | F8: Director: Emerging Contractor Development | G8: Quarterly | H8: ='Register 2025-26'!V16 -> 0
A9: HSFP | B9: HSFP-4 | C9: Inability for the department to provide input on skills development to unemployed youth (apprenticeship and learning ) | E9: Enhance working relationship with the Construction Education Training Authority (CETA) to receive funding permanently for funding the learnership and apprenticeship programmes. | F9: Director: Emerging Contractor Development | G9: Annually | H9: ='Register 2025-26'!V17 -> 0
A10: HSFP | B10: HSFP-5 | C10: Appointed contractors may not adequately report on the number of jobs created | E10: The Directorate of Emerging Contractors in cooperation with the Project Managers, EPWP Coordinators, Hands On Support and ECDPWI to collect compliant data from the appointed contractors | F10: Director: Emerging Contractor Development | G10: Quarterly
A11: HSFP | B11: HSFP-6 | C11: Procurement of 10% building materials from black industrialists may not be achieved since there is no policy provision and provision in the contracts of the appointed contractors | E11: Conduct a survey amongst the contractors appointed in all Departmental Regions to determine percentage of Black Industrialists whose building materials is being procured by appointed contractor | F11: Director: Emerging Contractor Development | G11: 31/03/2025 | H11: ='Register 2025-26'!V19 -> 0
A12: HSFP | B12: HSFP-7 | C12: Delays in the processes of project approval | E12: The Risk has been tolerated in as far as the Risk Tolerance level, however risk is still managed. | F12: Director: Beneficiary Management | G12: Quarterly | H12: ='Register 2025-26'!V20 -> 0
A13: HSIP | B13: HSIP 1 | C13: Inadequate provision of temporary relief to emergency housing cases | E13: Engage and support relevant stakeholders on policy implementation | F13: Director: Emergency Housing and EPHP | G13: Quarterly | H13: ='Register 2025-26'!V21 -> 0
A14: HSIP | B14: HSIP 2 | C14: Inconsistence in the implementation of the EPHP programme | E14: Conduct workshops for appointed CRO's to reinforce the understanding | F14: Director: Emergency Housing and EPHP | G14: Quarterly | H14: ='Register 2025-26'!V22 -> 0
A15: HSIP | B15: HSIP 3 | C15: Inability to upgrade informal settlements to the desired phases 1, 2 & 3 | E15: Review province wide upgrading strategy to align with DORA and the National Human Settlements upgrading framework | F15: Director: Informal Settlements Upgrading | G15: 30/09/2025 | H15: ='Register 2025-26'!V23 -> 0
A16: HSPA | B16: HSPA- 01 | C16: Inadequate devolution of land parcels to municipalities | E16: Engage municipalities to provide council resolutions/regulations and or development plans inline with the land to be devolved | F16: Director: Land Acquisition and Tenure Services | G16: Quarterly | H16: ='Register 2025-26'!V24 -> 0
A17: HSPA | B17: HSPA- 02 | C17: Inadequate number of pre-1994 housing stock transferred to beneficiaries | E17: Provision of support to municipalities to ensure completeness of beneficiary list | F17: Director: Sales, Transfers and Assets | G17: Quarterly Quarterly Quarterly | H17: ='Register 2025-26'!V25 -> 0
A18: HSPA | B18: HSPA- 03 | C18: Inadequate number of First Home Finance subsidies disbursed | E18: Continuous engagements with First Home Finance stakeholders | F18: Director:Social and Rental Housing Programme | G18: Quarterly | H18: ='Register 2025-26'!V26 -> 0
A19: HSPA | B19: HSPA- 04 | C19: Potential delays in resolving complex rental cases | E19: The Risk has been tolerated in as far as the Risk Tolerance level, however risk is still managed. | F19: Director:Social and Rental Housing Programme | G19: Quarterly | H19: ='Register 2025-26'!V27 -> 0
A20: FMS | B20: CFO-01 | C20: Non adherence to SCM processes and procedures | E20: Training of SCM practitioners and Bid Committee Members | F20: Director: SCM | G20: 31/12/2025 | H20: ='Register 2025-26'!V28 -> 0
A21: FMS | B21: CFO-02 | C21: Misuse of government vehicles | E21: Conduct awareness sessions on Fleet Management Policy | F21: Director : Asset Management | G21: Quarterly | H21: ='Register 2025-26'!V29 -> 0
A22: FMS | B22: CFO-03 | C22: Loss of Assets and consumables | E22: Conduct awareness campaigns on asset management during asset verification. | F22: Director : Asset Management | G22: bi-annually | H22: ='Register 2025-26'!V30 -> 0
... A39: S&S | B39: SM-04 | C39: Inconsistent stakeholder participation in integrated Human Settlements delivery | E39: Implementation of the stakeholder engagement and IGR action plan | F39: Director: Stakeholder Engagement | G39: Quarterly | H39: ='Register 2025-26'!V47 -> 0
H42: =+#REF!/#REF! -> #REF!

Sheet Sheet1
A1: High | B1: 15-25 [Risk Severely Affects Objective Accept with Rigorous/ Continuous Monitoring]
A3: Medium | B3: 5-14 [Risk Severely Affects Objective Accept with Rigorous/ Continuous Monitoring]
A5: Low | B5: 1-4 [Risk has little effect on Objective -Accept with Minor Monitoring]

Sheet Rating 
A4: This is a process to modify or respond to risk. Risk response can involve one or a combination of:
A6: Tolerate/Accept: an informed decision to tolerate or take on a particular risk
A7: Terminate/Avoid: an informed decision not to be involved in, or to withdraw from, an activity, in order not to be exposed to a particular risk.
A8: Treat /Mitigate: Form of risk response involving actions designed to reduce a risk or its consequences.
A9: Transfer/Sharing,risk: Form of risk response, involving contractual risk transfer to other parties, including insurance.
A12: The following is a rating table that will be utilised to categorise the various levels of inherent risk.
A14: Risk rating | B14: Inherent risk magnitude | C14: Response
A15: 15 - 25 | B15: High | C15: Unacceptable level of risk “ High level of control intervention required to achieve an acceptable level of residual risk”
A16: 5 -14 | B16: Medium | C16: Moderately acceptable level of risk “ Moderate level of control intervention required to achieve an acceptable level of residual risk”
A17: 1 - 4 | B17: Low | C17: Acceptable “ Low level of control intervention required, if any”
A19: The following is a rating table that will be utilised to categorise the various levels of residual risk.
A21: Risk rating | B21: Residual risk magnitude | C21: Response
A22: 15 - 25 | B22: High | C22: Unacceptable level of residual risk “Implies that the controls are either fundamentally inadequate (poor design) or ineffective (poor implementation). Controls require substantial redesign, or a greater emphasis on proper implementation.
A23: 5 - 14 | B23: Medium | C23: Moderately Acceptable level of residual risk “Implies that the controls are either inadequate (poor design) or ineffective (poor implementation).
C24: Controls require some redesign, or a more emphasis on proper implementation.
A25: 1 - 4 | B25: Low | C25: Mostly acceptable level of residual risk “Requires minimal control improvements”.
